{
"meta":{"test_sets":[],"test_metrics":[],"learn_metrics":[{"best_value":"Min","name":"RMSE"}],"launch_mode":"Train","parameters":"","iteration_count":1000,"learn_sets":["learn"],"name":"experiment"},
"iterations":[
{"learn":[14.59871775],"iteration":0,"passed_time":0.05645661786,"remaining_time":56.40016124},
{"learn":[14.22518863],"iteration":1,"passed_time":0.0579281,"remaining_time":28.9061219},
{"learn":[13.8866124],"iteration":2,"passed_time":0.05857067943,"remaining_time":19.46498913},
{"learn":[13.52356875],"iteration":3,"passed_time":0.0591539127,"remaining_time":14.72932426},
{"learn":[13.18870211],"iteration":4,"passed_time":0.05970087108,"remaining_time":11.88047334},
{"learn":[12.9124226],"iteration":5,"passed_time":0.06013685094,"remaining_time":9.96267164},
{"learn":[12.60003351],"iteration":6,"passed_time":0.06061612826,"remaining_time":8.598830766},
{"learn":[12.32990573],"iteration":7,"passed_time":0.06111449973,"remaining_time":7.578197967},
{"learn":[12.0660619],"iteration":8,"passed_time":0.06152480367,"remaining_time":6.774564493},
{"learn":[11.77309809],"iteration":9,"passed_time":0.06192480919,"remaining_time":6.13055611},
{"learn":[11.49227636],"iteration":10,"passed_time":0.06243349912,"remaining_time":5.613339148},
{"learn":[11.26264833],"iteration":11,"passed_time":0.06291087303,"remaining_time":5.179661879},
{"learn":[11.04260393],"iteration":12,"passed_time":0.06339160295,"remaining_time":4.812885547},
{"learn":[10.79916926],"iteration":13,"passed_time":0.0638820803,"remaining_time":4.499123655},
{"learn":[10.5541002],"iteration":14,"passed_time":0.06435784132,"remaining_time":4.226164914},
{"learn":[10.31918115],"iteration":15,"passed_time":0.06480035287,"remaining_time":3.985221702},
{"learn":[10.10004441],"iteration":16,"passed_time":0.0653792584,"remaining_time":3.780459471},
{"learn":[9.894556723],"iteration":17,"passed_time":0.06592764935,"remaining_time":3.596719537},
{"learn":[9.690174082],"iteration":18,"passed_time":0.06652633063,"remaining_time":3.434859492},
{"learn":[9.506034866],"iteration":19,"passed_time":0.06709126116,"remaining_time":3.287471797},
{"learn":[9.338524633],"iteration":20,"passed_time":0.06766615952,"remaining_time":3.154531913},
{"learn":[9.170203312],"iteration":21,"passed_time":0.06827383652,"remaining_time":3.035082369},
{"learn":[9.010299969],"iteration":22,"passed_time":0.06874922688,"remaining_time":2.920347594},
{"learn":[8.843866678],"iteration":23,"passed_time":0.06934030418,"remaining_time":2.819839037},
{"learn":[8.690548059],"iteration":24,"passed_time":0.06999705319,"remaining_time":2.729885074},
{"learn":[8.555307687],"iteration":25,"passed_time":0.07140373942,"remaining_time":2.674893931},
{"learn":[8.413851302],"iteration":26,"passed_time":0.07250653206,"remaining_time":2.612920581},
{"learn":[8.29256019],"iteration":27,"passed_time":0.07307225401,"remaining_time":2.536651104},
{"learn":[8.162193833],"iteration":28,"passed_time":0.07350781313,"remaining_time":2.461244364},
{"learn":[8.040736294],"iteration":29,"passed_time":0.07392955753,"remaining_time":2.390389027},
{"learn":[7.921220278],"iteration":30,"passed_time":0.07433341995,"remaining_time":2.323518836},
{"learn":[7.809589039],"iteration":31,"passed_time":0.07478301417,"remaining_time":2.262186179},
{"learn":[7.699675801],"iteration":32,"passed_time":0.07538283711,"remaining_time":2.20894556},
{"learn":[7.60645267],"iteration":33,"passed_time":0.07601505801,"remaining_time":2.159721942},
{"learn":[7.498880302],"iteration":34,"passed_time":0.07653128141,"remaining_time":2.110076759},
{"learn":[7.401158744],"iteration":35,"passed_time":0.07689665498,"remaining_time":2.059121539},
{"learn":[7.306431077],"iteration":36,"passed_time":0.07745696725,"remaining_time":2.01597458},
{"learn":[7.223863468],"iteration":37,"passed_time":0.07800604943,"remaining_time":1.974784725},
{"learn":[7.143477682],"iteration":38,"passed_time":0.07859965125,"remaining_time":1.936776022},
{"learn":[7.062817131],"iteration":39,"passed_time":0.0791555957,"remaining_time":1.899734297},
{"learn":[6.990793435],"iteration":40,"passed_time":0.07959042351,"remaining_time":1.861639418},
{"learn":[6.931862224],"iteration":41,"passed_time":0.08015472291,"remaining_time":1.828291061},
{"learn":[6.858296558],"iteration":42,"passed_time":0.08077432663,"remaining_time":1.797698386},
{"learn":[6.786268161],"iteration":43,"passed_time":0.08199741907,"remaining_time":1.781580287},
{"learn":[6.717118549],"iteration":44,"passed_time":0.08335490307,"remaining_time":1.768976276},
{"learn":[6.652948106],"iteration":45,"passed_time":0.08445375288,"remaining_time":1.751497397},
{"learn":[6.589686076],"iteration":46,"passed_time":0.08486785362,"remaining_time":1.720831159},
{"learn":[6.531283097],"iteration":47,"passed_time":0.08536722688,"remaining_time":1.693116666},
{"learn":[6.471368031],"iteration":48,"passed_time":0.08587762062,"remaining_time":1.666726882},
{"learn":[6.416481395],"iteration":49,"passed_time":0.08637779532,"remaining_time":1.641178111},
{"learn":[6.369870822],"iteration":50,"passed_time":0.08687838075,"remaining_time":1.616619281},
{"learn":[6.325678067],"iteration":51,"passed_time":0.08735830923,"remaining_time":1.592609176},
{"learn":[6.275766122],"iteration":52,"passed_time":0.08788058847,"remaining_time":1.570243722},
{"learn":[6.224773967],"iteration":53,"passed_time":0.08830238296,"remaining_time":1.546926931},
{"learn":[6.182249254],"iteration":54,"passed_time":0.08880436089,"remaining_time":1.525820383},
{"learn":[6.139904173],"iteration":55,"passed_time":0.08922925092,"remaining_time":1.50415023},
{"learn":[6.100525536],"iteration":56,"passed_time":0.08972818339,"remaining_time":1.484450473},
{"learn":[6.062568564],"iteration":57,"passed_time":0.09023973845,"remaining_time":1.465617821},
{"learn":[6.030559288],"iteration":58,"passed_time":0.09087111784,"remaining_time":1.44931732},
{"learn":[5.997931376],"iteration":59,"passed_time":0.09188230662,"remaining_time":1.43948947},
{"learn":[5.964103835],"iteration":60,"passed_time":0.09234559534,"remaining_time":1.421516623},
{"learn":[5.933729724],"iteration":61,"passed_time":0.09291308044,"remaining_time":1.405684991},
{"learn":[5.901932711],"iteration":62,"passed_time":0.09338245003,"remaining_time":1.388878662},
{"learn":[5.873727795],"iteration":63,"passed_time":0.09384373516,"remaining_time":1.372464627},
{"learn":[5.846485734],"iteration":64,"passed_time":0.09435800508,"remaining_time":1.357303611},
{"learn":[5.820630862],"iteration":65,"passed_time":0.09485194863,"remaining_time":1.342298788},
{"learn":[5.793646238],"iteration":66,"passed_time":0.09539641255,"remaining_time":1.32843064},
{"learn":[5.765388646],"iteration":67,"passed_time":0.09590487206,"remaining_time":1.314460894},
{"learn":[5.747073912],"iteration":68,"passed_time":0.09664971865,"remaining_time":1.304070842},
{"learn":[5.722315217],"iteration":69,"passed_time":0.09715825831,"remaining_time":1.29081686},
{"learn":[5.699970599],"iteration":70,"passed_time":0.099077281,"remaining_time":1.296377381},
{"learn":[5.682732647],"iteration":71,"passed_time":0.09988023268,"remaining_time":1.287345221},
{"learn":[5.663525791],"iteration":72,"passed_time":0.1007531688,"remaining_time":1.279427225},
{"learn":[5.642381613],"iteration":73,"passed_time":0.1017688753,"remaining_time":1.273486196},
{"learn":[5.621404779],"iteration":74,"passed_time":0.1022741791,"remaining_time":1.261381543},
{"learn":[5.602460129],"iteration":75,"passed_time":0.1030400591,"remaining_time":1.252750192},
{"learn":[5.587337574],"iteration":76,"passed_time":0.1034972569,"remaining_time":1.240622963},
{"learn":[5.572393026],"iteration":77,"passed_time":0.10395158,"remaining_time":1.228760984},
{"learn":[5.558425806],"iteration":78,"passed_time":0.1046611192,"remaining_time":1.220163174},
{"learn":[5.541518902],"iteration":79,"passed_time":0.1054702766,"remaining_time":1.212908181},
{"learn":[5.526157283],"iteration":80,"passed_time":0.1059044031,"remaining_time":1.201557364},
{"learn":[5.511746977],"iteration":81,"passed_time":0.1066874338,"remaining_time":1.194378832},
{"learn":[5.504975022],"iteration":82,"passed_time":0.1070561934,"remaining_time":1.182777462},
{"learn":[5.493980522],"iteration":83,"passed_time":0.107860392,"remaining_time":1.176191893},
{"learn":[5.480745463],"iteration":84,"passed_time":0.1083957796,"remaining_time":1.166848687},
{"learn":[5.464052013],"iteration":85,"passed_time":0.1091632324,"remaining_time":1.16017668},
{"learn":[5.449143727],"iteration":86,"passed_time":0.1096318006,"remaining_time":1.150503838},
{"learn":[5.438255432],"iteration":87,"passed_time":0.1101856012,"remaining_time":1.141923504},
{"learn":[5.425927931],"iteration":88,"passed_time":0.1107626735,"remaining_time":1.133761748},
{"learn":[5.412331217],"iteration":89,"passed_time":0.1116685439,"remaining_time":1.129093055},
{"learn":[5.400691499],"iteration":90,"passed_time":0.11217511,"remaining_time":1.120518406},
{"learn":[5.391618744],"iteration":91,"passed_time":0.1127161678,"remaining_time":1.112459569},
{"learn":[5.380766572],"iteration":92,"passed_time":0.1133665813,"remaining_time":1.105628916},
{"learn":[5.372207183],"iteration":93,"passed_time":0.1142183992,"remaining_time":1.100870954},
{"learn":[5.362918837],"iteration":94,"passed_time":0.1150530379,"remaining_time":1.096031572},
{"learn":[5.348292324],"iteration":95,"passed_time":0.1157990925,"remaining_time":1.090441454},
{"learn":[5.339772295],"iteration":96,"passed_time":0.1163700538,"remaining_time":1.083321222},
{"learn":[5.331515983],"iteration":97,"passed_time":0.1172873546,"remaining_time":1.079522386},
{"learn":[5.323861644],"iteration":98,"passed_time":0.1180405924,"remaining_time":1.074288624},
{"learn":[5.313277281],"iteration":99,"passed_time":0.1185651006,"remaining_time":1.067085905},
{"learn":[5.30685627],"iteration":100,"passed_time":0.1190738707,"remaining_time":1.059875344},
{"learn":[5.29652059],"iteration":101,"passed_time":0.1197398261,"remaining_time":1.054180038},
{"learn":[5.288350766],"iteration":102,"passed_time":0.1202905112,"remaining_time":1.047578529},
{"learn":[5.27993346],"iteration":103,"passed_time":0.1207808583,"remaining_time":1.040573548},
{"learn":[5.271789139],"iteration":104,"passed_time":0.1212193126,"remaining_time":1.033250331},
{"learn":[5.262684686],"iteration":105,"passed_time":0.1216619744,"remaining_time":1.026092501},
{"learn":[5.251619772],"iteration":106,"passed_time":0.1222119482,"remaining_time":1.019955792},
{"learn":[5.241012171],"iteration":107,"passed_time":0.1227286324,"remaining_time":1.013647594},
{"learn":[5.232684032],"iteration":108,"passed_time":0.1232945948,"remaining_time":1.007848477},
{"learn":[5.224267141],"iteration":109,"passed_time":0.1238696434,"remaining_time":1.002218024},
{"learn":[5.216324968],"iteration":110,"passed_time":0.1245638452,"remaining_time":0.9976329584},
{"learn":[5.211102527],"iteration":111,"passed_time":0.1250231568,"remaining_time":0.9912550289},
{"learn":[5.206364257],"iteration":112,"passed_time":0.1254291631,"remaining_time":0.9845634303},
{"learn":[5.196937641],"iteration":113,"passed_time":0.1259614452,"remaining_time":0.9789635125},
{"learn":[5.190746047],"iteration":114,"passed_time":0.1264238022,"remaining_time":0.9729136085},
{"learn":[5.181885213],"iteration":115,"passed_time":0.127934785,"remaining_time":0.9749512928},
{"learn":[5.178293568],"iteration":116,"passed_time":0.1291296924,"remaining_time":0.9745428925},
{"learn":[5.170991438],"iteration":117,"passed_time":0.1299817666,"remaining_time":0.9715586284},
{"learn":[5.166257212],"iteration":118,"passed_time":0.131112495,"remaining_time":0.9706731772},
{"learn":[5.161421246],"iteration":119,"passed_time":0.1339820383,"remaining_time":0.9825349477},
{"learn":[5.158223542],"iteration":120,"passed_time":0.135465201,"remaining_time":0.9840819145},
{"learn":[5.15470988],"iteration":121,"passed_time":0.1370931992,"remaining_time":0.9866215486},
{"learn":[5.146388143],"iteration":122,"passed_time":0.1381106793,"remaining_time":0.9847403718},
{"learn":[5.139529364],"iteration":123,"passed_time":0.139129101,"remaining_time":0.982879778},
{"learn":[5.134276023],"iteration":124,"passed_time":0.1398682231,"remaining_time":0.9790775618},
{"learn":[5.128536065],"iteration":125,"passed_time":0.1408485267,"remaining_time":0.976996923},
{"learn":[5.123300353],"iteration":126,"passed_time":0.1415730927,"remaining_time":0.973175669},
{"learn":[5.116200518],"iteration":127,"passed_time":0.1421647911,"remaining_time":0.9684976397},
{"learn":[5.108728704],"iteration":128,"passed_time":0.1426284405,"remaining_time":0.9630183852},
{"learn":[5.104075866],"iteration":129,"passed_time":0.1430799782,"remaining_time":0.9575352388},
{"learn":[5.100317606],"iteration":130,"passed_time":0.1434719594,"remaining_time":0.9517338374},
{"learn":[5.095814182],"iteration":131,"passed_time":0.1439531201,"remaining_time":0.9466008198},
{"learn":[5.092146915],"iteration":132,"passed_time":0.1445515104,"remaining_time":0.9423019515},
{"learn":[5.085258329],"iteration":133,"passed_time":0.144972804,"remaining_time":0.9369137932},
{"learn":[5.079219421],"iteration":134,"passed_time":0.145475944,"remaining_time":0.9321236414},
{"learn":[5.076476829],"iteration":135,"passed_time":0.1460376789,"remaining_time":0.9277687833},
{"learn":[5.072133867],"iteration":136,"passed_time":0.1465326442,"remaining_time":0.9230487005},
{"learn":[5.067031564],"iteration":137,"passed_time":0.1470798531,"remaining_time":0.9187161836},
{"learn":[5.061358312],"iteration":138,"passed_time":0.1475975291,"remaining_time":0.914255198},
{"learn":[5.056759124],"iteration":139,"passed_time":0.1480837688,"remaining_time":0.9096574371},
{"learn":[5.050254],"iteration":140,"passed_time":0.148595945,"remaining_time":0.9052760053},
{"learn":[5.048376474],"iteration":141,"passed_time":0.1488808747,"remaining_time":0.8995759892},
{"learn":[5.042603751],"iteration":142,"passed_time":0.149288604,"remaining_time":0.8946876478},
{"learn":[5.037477349],"iteration":143,"passed_time":0.1499056181,"remaining_time":0.8911056186},
{"learn":[5.03230489],"iteration":144,"passed_time":0.1506872821,"remaining_time":0.8885353529},
{"learn":[5.025976187],"iteration":145,"passed_time":0.1521045075,"remaining_time":0.889707188},
{"learn":[5.01952451],"iteration":146,"passed_time":0.1527251577,"remaining_time":0.8862214936},
{"learn":[5.017569424],"iteration":147,"passed_time":0.1533120676,"remaining_time":0.882580281},
{"learn":[5.008962367],"iteration":148,"passed_time":0.153892576,"remaining_time":0.8789435045},
{"learn":[5.003880266],"iteration":149,"passed_time":0.1543681367,"remaining_time":0.8747527744},
{"learn":[4.996387564],"iteration":150,"passed_time":0.1549380661,"remaining_time":0.871141842},
{"learn":[4.993361683],"iteration":151,"passed_time":0.1553697383,"remaining_time":0.8667995926},
{"learn":[4.99005752],"iteration":152,"passed_time":0.1557185723,"remaining_time":0.862049874},
{"learn":[4.986908764],"iteration":153,"passed_time":0.156148301,"remaining_time":0.8578017053},
{"learn":[4.985207175],"iteration":154,"passed_time":0.1565495988,"remaining_time":0.8534478127},
{"learn":[4.979003494],"iteration":155,"passed_time":0.1570609936,"remaining_time":0.8497402472},
{"learn":[4.973142217],"iteration":156,"passed_time":0.1574977749,"remaining_time":0.8456727656},
{"learn":[4.967056696],"iteration":157,"passed_time":0.1579625162,"remaining_time":0.8418002444},
{"learn":[4.961460696],"iteration":158,"passed_time":0.1584203051,"remaining_time":0.8379338148},
{"learn":[4.954240363],"iteration":159,"passed_time":0.158799283,"remaining_time":0.8336962355},
{"learn":[4.952320707],"iteration":160,"passed_time":0.1590937497,"remaining_time":0.8290661863},
{"learn":[4.948337777],"iteration":161,"passed_time":0.1595251413,"remaining_time":0.8251979534},
{"learn":[4.943228639],"iteration":162,"passed_time":0.1599162109,"remaining_time":0.8211648375},
{"learn":[4.938545759],"iteration":163,"passed_time":0.160370243,"remaining_time":0.8174970926},
{"learn":[4.935330572],"iteration":164,"passed_time":0.160786718,"remaining_time":0.8136782397},
{"learn":[4.932051543],"iteration":165,"passed_time":0.1613227669,"remaining_time":0.81050113},
{"learn":[4.928964153],"iteration":166,"passed_time":0.1617234236,"remaining_time":0.8066803104},
{"learn":[4.922860227],"iteration":167,"passed_time":0.1622394073,"remaining_time":0.8034713505},
{"learn":[4.917668772],"iteration":168,"passed_time":0.1626606709,"remaining_time":0.7998285058},
{"learn":[4.910365386],"iteration":169,"passed_time":0.1631056268,"remaining_time":0.7963392366},
{"learn":[4.906457206],"iteration":170,"passed_time":0.1635924364,"remaining_time":0.7930884783},
{"learn":[4.901996508],"iteration":171,"passed_time":0.1659817908,"remaining_time":0.7990286208},
{"learn":[4.896816173],"iteration":172,"passed_time":0.1669834479,"remaining_time":0.7982387944},
{"learn":[4.891123132],"iteration":173,"passed_time":0.1675676028,"remaining_time":0.7954645974},
{"learn":[4.887630202],"iteration":174,"passed_time":0.1681381234,"remaining_time":0.792651153},
{"learn":[4.885259712],"iteration":175,"passed_time":0.1685715787,"remaining_time":0.7892214822},
{"learn":[4.880659728],"iteration":176,"passed_time":0.1690699502,"remaining_time":0.7861275085},
{"learn":[4.877299723],"iteration":177,"passed_time":0.1695622608,"remaining_time":0.7830347101},
{"learn":[4.874038772],"iteration":178,"passed_time":0.1700052733,"remaining_time":0.7797448567},
{"learn":[4.86943698],"iteration":179,"passed_time":0.1704446492,"remaining_time":0.7764700686},
{"learn":[4.861268711],"iteration":180,"passed_time":0.1709456354,"remaining_time":0.7735053887},
{"learn":[4.858673056],"iteration":181,"passed_time":0.1713463922,"remaining_time":0.7701173013},
{"learn":[4.854036207],"iteration":182,"passed_time":0.1718632167,"remaining_time":0.767280044},
{"learn":[4.85130244],"iteration":183,"passed_time":0.1723806823,"remaining_time":0.7644708521},
{"learn":[4.847510084],"iteration":184,"passed_time":0.1727942721,"remaining_time":0.7612288205},
{"learn":[4.845691673],"iteration":185,"passed_time":0.1732920926,"remaining_time":0.7583858247},
{"learn":[4.842058646],"iteration":186,"passed_time":0.1737996004,"remaining_time":0.7556100276},
{"learn":[4.838623675],"iteration":187,"passed_time":0.17428012,"remaining_time":0.7527417948},
{"learn":[4.834602161],"iteration":188,"passed_time":0.1747411346,"remaining_time":0.7498151333},
{"learn":[4.830858976],"iteration":189,"passed_time":0.1751512482,"remaining_time":0.7466974267},
{"learn":[4.827590511],"iteration":190,"passed_time":0.1755901032,"remaining_time":0.743729809},
{"learn":[4.822246226],"iteration":191,"passed_time":0.1761578789,"remaining_time":0.7413310735},
{"learn":[4.816686395],"iteration":192,"passed_time":0.176620286,"remaining_time":0.7385107295},
{"learn":[4.814797121],"iteration":193,"passed_time":0.1772062642,"remaining_time":0.7362280873},
{"learn":[4.811639392],"iteration":194,"passed_time":0.1776608273,"remaining_time":0.7334203383},
{"learn":[4.804813432],"iteration":195,"passed_time":0.1781250377,"remaining_time":0.7306761749},
{"learn":[4.80251613],"iteration":196,"passed_time":0.1794791398,"remaining_time":0.7315824837},
{"learn":[4.800087884],"iteration":197,"passed_time":0.1809345228,"remaining_time":0.7328761984},
{"learn":[4.794773135],"iteration":198,"passed_time":0.1820049078,"remaining_time":0.732592619},
{"learn":[4.791664833],"iteration":199,"passed_time":0.1825599615,"remaining_time":0.7302398459},
{"learn":[4.785989873],"iteration":200,"passed_time":0.183040461,"remaining_time":0.7276085986},
{"learn":[4.782387142],"iteration":201,"passed_time":0.1835104717,"remaining_time":0.7249572101},
{"learn":[4.778623704],"iteration":202,"passed_time":0.1839179606,"remaining_time":0.7220818454},
{"learn":[4.775772178],"iteration":203,"passed_time":0.1846611897,"remaining_time":0.7205407206},
{"learn":[4.77023101],"iteration":204,"passed_time":0.1851341958,"remaining_time":0.7179594423},
{"learn":[4.764496689],"iteration":205,"passed_time":0.1856858626,"remaining_time":0.71570182},
{"learn":[4.763138716],"iteration":206,"passed_time":0.1860719833,"remaining_time":0.7128264867},
{"learn":[4.758053283],"iteration":207,"passed_time":0.1865577923,"remaining_time":0.7103546706},
{"learn":[4.755063788],"iteration":208,"passed_time":0.1869426808,"remaining_time":0.7075199066},
{"learn":[4.752465267],"iteration":209,"passed_time":0.187355379,"remaining_time":0.7048130924},
{"learn":[4.748067377],"iteration":210,"passed_time":0.1877642403,"remaining_time":0.702113676},
{"learn":[4.744163298],"iteration":211,"passed_time":0.1882390897,"remaining_time":0.6996811449},
{"learn":[4.736670896],"iteration":212,"passed_time":0.1886563762,"remaining_time":0.6970543101},
{"learn":[4.73349255],"iteration":213,"passed_time":0.189076127,"remaining_time":0.6944571768},
{"learn":[4.731864595],"iteration":214,"passed_time":0.1895344669,"remaining_time":0.692021193},
{"learn":[4.728398311],"iteration":215,"passed_time":0.1899855538,"remaining_time":0.6895771951},
{"learn":[4.723865975],"iteration":216,"passed_time":0.1904506557,"remaining_time":0.6872021356},
{"learn":[4.723483365],"iteration":217,"passed_time":0.1908221302,"remaining_time":0.6845087423},
{"learn":[4.72095416],"iteration":218,"passed_time":0.1912629387,"remaining_time":0.6820838134},
{"learn":[4.716173382],"iteration":219,"passed_time":0.1917836001,"remaining_time":0.6799600366},
{"learn":[4.710563974],"iteration":220,"passed_time":0.1923227645,"remaining_time":0.6779159889},
{"learn":[4.707160263],"iteration":221,"passed_time":0.1930407889,"remaining_time":0.6765123142},
{"learn":[4.70408351],"iteration":222,"passed_time":0.1942947161,"remaining_time":0.6769820377},
{"learn":[4.702501831],"iteration":223,"passed_time":0.1953746078,"remaining_time":0.6768334626},
{"learn":[4.700269738],"iteration":224,"passed_time":0.1958795209,"remaining_time":0.6746961277},
{"learn":[4.695346302],"iteration":225,"passed_time":0.1963314902,"remaining_time":0.6723919177},
{"learn":[4.689769299],"iteration":226,"passed_time":0.1968644034,"remaining_time":0.6703796646},
{"learn":[4.687919514],"iteration":227,"passed_time":0.1972675045,"remaining_time":0.6679408485},
{"learn":[4.682982074],"iteration":228,"passed_time":0.1977246923,"remaining_time":0.6657019116},
{"learn":[4.679578702],"iteration":229,"passed_time":0.1980867499,"remaining_time":0.6631599889},
{"learn":[4.675751423],"iteration":230,"passed_time":0.1985146053,"remaining_time":0.6608559803},
{"learn":[4.672710726],"iteration":231,"passed_time":0.1988842665,"remaining_time":0.6583755029},
{"learn":[4.6690533],"iteration":232,"passed_time":0.1994284299,"remaining_time":0.6564875782},
{"learn":[4.667595702],"iteration":233,"passed_time":0.1998426108,"remaining_time":0.6541856404},
{"learn":[4.664241291],"iteration":234,"passed_time":0.2003075725,"remaining_time":0.6520650763},
{"learn":[4.662246999],"iteration":235,"passed_time":0.2008159719,"remaining_time":0.6500991632},
{"learn":[4.658668443],"iteration":236,"passed_time":0.201226356,"remaining_time":0.6478299983},
{"learn":[4.658017572],"iteration":237,"passed_time":0.2016838643,"remaining_time":0.6457273304},
{"learn":[4.657656705],"iteration":238,"passed_time":0.2021272875,"remaining_time":0.6435935808},
{"learn":[4.653242871],"iteration":239,"passed_time":0.2025376516,"remaining_time":0.64136923},
{"learn":[4.6507302],"iteration":240,"passed_time":0.2029797925,"remaining_time":0.6392600103},
{"learn":[4.647671336],"iteration":241,"passed_time":0.2035276625,"remaining_time":0.6374957362},
{"learn":[4.645506007],"iteration":242,"passed_time":0.2040559875,"remaining_time":0.6356805866},
{"learn":[4.641297906],"iteration":243,"passed_time":0.2045108111,"remaining_time":0.6336482508},
{"learn":[4.63798107],"iteration":244,"passed_time":0.2052198193,"remaining_time":0.6324120964},
{"learn":[4.635062318],"iteration":245,"passed_time":0.2056934866,"remaining_time":0.630458898},
{"learn":[4.631606017],"iteration":246,"passed_time":0.2062075662,"remaining_time":0.6286408799},
{"learn":[4.630215494],"iteration":247,"passed_time":0.206654155,"remaining_time":0.6266287282},
{"learn":[4.62729814],"iteration":248,"passed_time":0.2073638638,"remaining_time":0.6254227377},
{"learn":[4.624691756],"iteration":249,"passed_time":0.2082503545,"remaining_time":0.6247510635},
{"learn":[4.621840053],"iteration":250,"passed_time":0.2093759221,"remaining_time":0.6247910983},
{"learn":[4.619602091],"iteration":251,"passed_time":0.2103630074,"remaining_time":0.6244108315},
{"learn":[4.613584029],"iteration":252,"passed_time":0.2107623317,"remaining_time":0.6222903628},
{"learn":[4.6119388],"iteration":253,"passed_time":0.2112174562,"remaining_time":0.620347332},
{"learn":[4.60870702],"iteration":254,"passed_time":0.2116671005,"remaining_time":0.6183999603},
{"learn":[4.604771557],"iteration":255,"passed_time":0.2120436441,"remaining_time":0.6162518405},
{"learn":[4.604231277],"iteration":256,"passed_time":0.2124692153,"remaining_time":0.6142592489},
{"learn":[4.600750354],"iteration":257,"passed_time":0.2129043537,"remaining_time":0.6123063195},
{"learn":[4.596488253],"iteration":258,"passed_time":0.2133972854,"remaining_time":0.6105304575},
{"learn":[4.59470784],"iteration":259,"passed_time":0.2137804207,"remaining_time":0.6084519667},
{"learn":[4.588818005],"iteration":260,"passed_time":0.2141746259,"remaining_time":0.6064178105},
{"learn":[4.585054174],"iteration":261,"passed_time":0.2146667562,"remaining_time":0.6046720079},
{"learn":[4.581471435],"iteration":262,"passed_time":0.2150539388,"remaining_time":0.6026416459},
{"learn":[4.577555199],"iteration":263,"passed_time":0.2154674685,"remaining_time":0.6006971849},
{"learn":[4.57457145],"iteration":264,"passed_time":0.2159550306,"remaining_time":0.5989696132},
{"learn":[4.573029224],"iteration":265,"passed_time":0.2163831264,"remaining_time":0.5970872736},
{"learn":[4.571326203],"iteration":266,"passed_time":0.21683236,"remaining_time":0.5952738571},
{"learn":[4.571019224],"iteration":267,"passed_time":0.217221486,"remaining_time":0.5933064469},
{"learn":[4.565766631],"iteration":268,"passed_time":0.2176074063,"remaining_time":0.5913420596},
{"learn":[4.563383471],"iteration":269,"passed_time":0.2181899183,"remaining_time":0.5899208903},
{"learn":[4.558165805],"iteration":270,"passed_time":0.2187037575,"remaining_time":0.5883211778},
{"learn":[4.55629209],"iteration":271,"passed_time":0.219413457,"remaining_time":0.5872536642},
{"learn":[4.549383848],"iteration":272,"passed_time":0.2199843081,"remaining_time":0.5858190182},
{"learn":[4.546227503],"iteration":273,"passed_time":0.220437639,"remaining_time":0.5840792916},
{"learn":[4.540620977],"iteration":274,"passed_time":0.2209226065,"remaining_time":0.5824323261},
{"learn":[4.532898237],"iteration":275,"passed_time":0.2217395177,"remaining_time":0.581664532},
{"learn":[4.529757367],"iteration":276,"passed_time":0.2222340523,"remaining_time":0.5800549453},
{"learn":[4.52579294],"iteration":277,"passed_time":0.2227946652,"remaining_time":0.5786249937},
{"learn":[4.521572155],"iteration":278,"passed_time":0.2233834083,"remaining_time":0.5772739691},
{"learn":[4.518818099],"iteration":279,"passed_time":0.2242567104,"remaining_time":0.5766601125},
{"learn":[4.514012334],"iteration":280,"passed_time":0.2247752279,"remaining_time":0.5751366152},
{"learn":[4.508331416],"iteration":281,"passed_time":0.2251615389,"remaining_time":0.5732836346},
{"learn":[4.506038537],"iteration":282,"passed_time":0.2257050512,"remaining_time":0.5718392992},
{"learn":[4.505805643],"iteration":283,"passed_time":0.2261575506,"remaining_time":0.5701718529},
{"learn":[4.501550352],"iteration":284,"passed_time":0.2266252873,"remaining_time":0.5685511592},
{"learn":[4.494692643],"iteration":285,"passed_time":0.227036042,"remaining_time":0.5667962727},
{"learn":[4.489330245],"iteration":286,"passed_time":0.2275706583,"remaining_time":0.5653584647},
{"learn":[4.484826955],"iteration":287,"passed_time":0.2281225655,"remaining_time":0.5639696759},
{"learn":[4.478285428],"iteration":288,"passed_time":0.2285403028,"remaining_time":0.5622565926},
{"learn":[4.475311671],"iteration":289,"passed_time":0.2289273551,"remaining_time":0.5604773177},
{"learn":[4.471581298],"iteration":290,"passed_time":0.2293366673,"remaining_time":0.5587618457},
{"learn":[4.469164956],"iteration":291,"passed_time":0.2297842078,"remaining_time":0.5571480108},
{"learn":[4.462068024],"iteration":292,"passed_time":0.2302378192,"remaining_time":0.5555567857},
{"learn":[4.458540976],"iteration":293,"passed_time":0.2306833863,"remaining_time":0.553953982},
{"learn":[4.455757458],"iteration":294,"passed_time":0.2311643466,"remaining_time":0.5524436079},
{"learn":[4.453027414],"iteration":295,"passed_time":0.2317514868,"remaining_time":0.5511927255},
{"learn":[4.450659338],"iteration":296,"passed_time":0.2322289108,"remaining_time":0.5496866139},
{"learn":[4.444696901],"iteration":297,"passed_time":0.2328301421,"remaining_time":0.5484790595},
{"learn":[4.442052813],"iteration":298,"passed_time":0.2332545613,"remaining_time":0.5468610282},
{"learn":[4.440036756],"iteration":299,"passed_time":0.2337677693,"remaining_time":0.5454581283},
{"learn":[4.435017051],"iteration":300,"passed_time":0.2341720825,"remaining_time":0.543808258},
{"learn":[4.429962125],"iteration":301,"passed_time":0.2346295708,"remaining_time":0.5422895379},
{"learn":[4.427666256],"iteration":302,"passed_time":0.2349933816,"remaining_time":0.5405623333},
{"learn":[4.425030004],"iteration":303,"passed_time":0.2354668886,"remaining_time":0.539095245},
{"learn":[4.422588771],"iteration":304,"passed_time":0.2360617627,"remaining_time":0.5379112297},
{"learn":[4.418936667],"iteration":305,"passed_time":0.2366930018,"remaining_time":0.5368135401},
{"learn":[4.416887976],"iteration":306,"passed_time":0.2374591723,"remaining_time":0.5360234737},
{"learn":[4.413773354],"iteration":307,"passed_time":0.2380229408,"remaining_time":0.534778815},
{"learn":[4.411129391],"iteration":308,"passed_time":0.238613978,"remaining_time":0.5335995431},
{"learn":[4.40850819],"iteration":309,"passed_time":0.2391382658,"remaining_time":0.532275495},
{"learn":[4.404880292],"iteration":310,"passed_time":0.2396066938,"remaining_time":0.530832836},
{"learn":[4.404593827],"iteration":311,"passed_time":0.2400522407,"remaining_time":0.5293459668},
{"learn":[4.402139942],"iteration":312,"passed_time":0.2405634852,"remaining_time":0.52800995},
{"learn":[4.400284725],"iteration":313,"passed_time":0.2409379851,"remaining_time":0.5263804389},
{"learn":[4.395805521],"iteration":314,"passed_time":0.2413148893,"remaining_time":0.5247641244},
{"learn":[4.392838833],"iteration":315,"passed_time":0.2417185213,"remaining_time":0.5232135082},
{"learn":[4.389213061],"iteration":316,"passed_time":0.2421664025,"remaining_time":0.5217654666},
{"learn":[4.3861981],"iteration":317,"passed_time":0.2426588534,"remaining_time":0.5204193019},
{"learn":[4.385054234],"iteration":318,"passed_time":0.2430591194,"remaining_time":0.5188816937},
{"learn":[4.379364607],"iteration":319,"passed_time":0.2435090041,"remaining_time":0.5174566337},
{"learn":[4.378387619],"iteration":320,"passed_time":0.2441385101,"remaining_time":0.5164175962},
{"learn":[4.375816727],"iteration":321,"passed_time":0.2446523893,"remaining_time":0.5151376397},
{"learn":[4.374600202],"iteration":322,"passed_time":0.245151983,"remaining_time":0.5138324845},
{"learn":[4.37098897],"iteration":323,"passed_time":0.2459382537,"remaining_time":0.5131304305},
{"learn":[4.367418484],"iteration":324,"passed_time":0.246619493,"remaining_time":0.5122097163},
{"learn":[4.363584638],"iteration":325,"passed_time":0.2471841531,"remaining_time":0.5110494453},
{"learn":[4.360770706],"iteration":326,"passed_time":0.2477003264,"remaining_time":0.5097930265},
{"learn":[4.358675808],"iteration":327,"passed_time":0.248109899,"remaining_time":0.50832272},
{"learn":[4.354228195],"iteration":328,"passed_time":0.2486852174,"remaining_time":0.5071969023},
{"learn":[4.353773425],"iteration":329,"passed_time":0.2490699456,"remaining_time":0.5056874652},
{"learn":[4.351648009],"iteration":330,"passed_time":0.2495273037,"remaining_time":0.5043316198},
{"learn":[4.348209927],"iteration":331,"passed_time":0.2500310105,"remaining_time":0.5030744427},
{"learn":[4.345852733],"iteration":332,"passed_time":0.2507211191,"remaining_time":0.5021951545},
{"learn":[4.34237339],"iteration":333,"passed_time":0.2514521167,"remaining_time":0.5013985321},
{"learn":[4.340814362],"iteration":334,"passed_time":0.2520821537,"remaining_time":0.5004018872},
{"learn":[4.339707068],"iteration":335,"passed_time":0.2526086755,"remaining_time":0.4992028588},
{"learn":[4.335430786],"iteration":336,"passed_time":0.2530262525,"remaining_time":0.4977934878},
{"learn":[4.33521887],"iteration":337,"passed_time":0.2534664098,"remaining_time":0.496434211},
{"learn":[4.328507238],"iteration":338,"passed_time":0.253891941,"remaining_time":0.4950518378},
{"learn":[4.326140732],"iteration":339,"passed_time":0.2543437893,"remaining_time":0.4937261791},
{"learn":[4.323785636],"iteration":340,"passed_time":0.2546963198,"remaining_time":0.492213709},
{"learn":[4.320632534],"iteration":341,"passed_time":0.2551613617,"remaining_time":0.4909244912},
{"learn":[4.31973724],"iteration":342,"passed_time":0.2556630892,"remaining_time":0.4897103487},
{"learn":[4.318000924],"iteration":343,"passed_time":0.2562526838,"remaining_time":0.4886679087},
{"learn":[4.312713628],"iteration":344,"passed_time":0.2567343454,"remaining_time":0.4874231775},
{"learn":[4.308220789],"iteration":345,"passed_time":0.2572213566,"remaining_time":0.4861929687},
{"learn":[4.305890947],"iteration":346,"passed_time":0.2576067559,"remaining_time":0.484775826},
{"learn":[4.305137856],"iteration":347,"passed_time":0.2580245333,"remaining_time":0.4834252749},
{"learn":[4.304787172],"iteration":348,"passed_time":0.2584515671,"remaining_time":0.4820973358},
{"learn":[4.30350134],"iteration":349,"passed_time":0.259205626,"remaining_time":0.4813818768},
{"learn":[4.30293809],"iteration":350,"passed_time":0.2596776603,"remaining_time":0.4801447337},
{"learn":[4.299548459],"iteration":351,"passed_time":0.2601429226,"remaining_time":0.4788994711},
{"learn":[4.294768408],"iteration":352,"passed_time":0.2606363853,"remaining_time":0.4777103152},
{"learn":[4.294581479],"iteration":353,"passed_time":0.2610844267,"remaining_time":0.4764422024},
{"learn":[4.292551604],"iteration":354,"passed_time":0.2614975156,"remaining_time":0.4751152044},
{"learn":[4.288628894],"iteration":355,"passed_time":0.261887383,"remaining_time":0.4737513333},
{"learn":[4.287802767],"iteration":356,"passed_time":0.262252987,"remaining_time":0.4723492174},
{"learn":[4.284566905],"iteration":357,"passed_time":0.26269632,"remaining_time":0.4710922834},
{"learn":[4.27890232],"iteration":358,"passed_time":0.2631934793,"remaining_time":0.4699359895},
{"learn":[4.276938023],"iteration":359,"passed_time":0.2635971714,"remaining_time":0.4686171936},
{"learn":[4.273425094],"iteration":360,"passed_time":0.2642203461,"remaining_time":0.46769197},
{"learn":[4.269726505],"iteration":361,"passed_time":0.2663678529,"remaining_time":0.4694549452},
{"learn":[4.265565857],"iteration":362,"passed_time":0.2674973237,"remaining_time":0.4694099041},
{"learn":[4.262117173],"iteration":363,"passed_time":0.268171594,"remaining_time":0.4685635544},
{"learn":[4.259185148],"iteration":364,"passed_time":0.2686491482,"remaining_time":0.4673759154},
{"learn":[4.257668507],"iteration":365,"passed_time":0.2690438743,"remaining_time":0.4660486785},
{"learn":[4.253432436],"iteration":366,"passed_time":0.2694838313,"remaining_time":0.4648045374},
{"learn":[4.250216667],"iteration":367,"passed_time":0.269956046,"remaining_time":0.4636201659},
{"learn":[4.24514828],"iteration":368,"passed_time":0.2704646658,"remaining_time":0.4625019081},
{"learn":[4.244015772],"iteration":369,"passed_time":0.2709357885,"remaining_time":0.4613230994},
{"learn":[4.240329192],"iteration":370,"passed_time":0.271386645,"remaining_time":0.4601137458},
{"learn":[4.236718014],"iteration":371,"passed_time":0.2717977403,"remaining_time":0.4588413466},
{"learn":[4.233495944],"iteration":372,"passed_time":0.2723285899,"remaining_time":0.4577748683},
{"learn":[4.230357491],"iteration":373,"passed_time":0.272788202,"remaining_time":0.4565920173},
{"learn":[4.227381215],"iteration":374,"passed_time":0.2732535044,"remaining_time":0.4554225073},
{"learn":[4.226169067],"iteration":375,"passed_time":0.2738186152,"remaining_time":0.4544223827},
{"learn":[4.225963861],"iteration":376,"passed_time":0.2742418523,"remaining_time":0.4531901167},
{"learn":[4.224346548],"iteration":377,"passed_time":0.2746552518,"remaining_time":0.4519459434},
{"learn":[4.222595381],"iteration":378,"passed_time":0.2750666477,"remaining_time":0.4507028712},
{"learn":[4.219700938],"iteration":379,"passed_time":0.2754418488,"remaining_time":0.4494051217},
{"learn":[4.216356207],"iteration":380,"passed_time":0.2758656569,"remaining_time":0.4481911854},
{"learn":[4.214326494],"iteration":381,"passed_time":0.2761795083,"remaining_time":0.4468034977},
{"learn":[4.212901398],"iteration":382,"passed_time":0.2766675213,"remaining_time":0.4457019859},
{"learn":[4.211331091],"iteration":383,"passed_time":0.277103992,"remaining_time":0.4445209872},
{"learn":[4.208624791],"iteration":384,"passed_time":0.2775282008,"remaining_time":0.4433242688},
{"learn":[4.204659106],"iteration":385,"passed_time":0.2779759217,"remaining_time":0.4421689531},
{"learn":[4.202968852],"iteration":386,"passed_time":0.2783222011,"remaining_time":0.4408566131},
{"learn":[4.197261935],"iteration":387,"passed_time":0.2790465876,"remaining_time":0.4401456485},
{"learn":[4.196934403],"iteration":388,"passed_time":0.2796955184,"remaining_time":0.439316097},
{"learn":[4.192479929],"iteration":389,"passed_time":0.2805733178,"remaining_time":0.4388454458},
{"learn":[4.190243116],"iteration":390,"passed_time":0.2812297821,"remaining_time":0.4380279726},
{"learn":[4.185852431],"iteration":391,"passed_time":0.2817270316,"remaining_time":0.4369643755},
{"learn":[4.180967944],"iteration":392,"passed_time":0.2822521909,"remaining_time":0.4359467682},
{"learn":[4.178283162],"iteration":393,"passed_time":0.28263181,"remaining_time":0.4347078093},
{"learn":[4.176341157],"iteration":394,"passed_time":0.2830610077,"remaining_time":0.4335491384},
{"learn":[4.176041504],"iteration":395,"passed_time":0.2835119744,"remaining_time":0.4324273549},
{"learn":[4.175564513],"iteration":396,"passed_time":0.2839914413,"remaining_time":0.4313522395},
{"learn":[4.170830274],"iteration":397,"passed_time":0.2844548001,"remaining_time":0.430255753},
{"learn":[4.167804808],"iteration":398,"passed_time":0.284899746,"remaining_time":0.4291347052},
{"learn":[4.165860548],"iteration":399,"passed_time":0.2852958045,"remaining_time":0.4279437067},
{"learn":[4.160950571],"iteration":400,"passed_time":0.2858991896,"remaining_time":0.4270663705},
{"learn":[4.158544115],"iteration":401,"passed_time":0.2867628788,"remaining_time":0.4265776157},
{"learn":[4.154448767],"iteration":402,"passed_time":0.2872568323,"remaining_time":0.4255392777},
{"learn":[4.15197457],"iteration":403,"passed_time":0.2877733162,"remaining_time":0.4245368724},
{"learn":[4.149562679],"iteration":404,"passed_time":0.2882719982,"remaining_time":0.4235107134},
{"learn":[4.149327961],"iteration":405,"passed_time":0.2888112328,"remaining_time":0.4225464834},
{"learn":[4.147444889],"iteration":406,"passed_time":0.2893758127,"remaining_time":0.4216212701},
{"learn":[4.147254809],"iteration":407,"passed_time":0.2899591562,"remaining_time":0.4207250501},
{"learn":[4.144589165],"iteration":408,"passed_time":0.2906462652,"remaining_time":0.4199803001},
{"learn":[4.141691034],"iteration":409,"passed_time":0.2911489644,"remaining_time":0.418970461},
{"learn":[4.138893468],"iteration":410,"passed_time":0.2925411648,"remaining_time":0.4192378249},
{"learn":[4.136964597],"iteration":411,"passed_time":0.2955840879,"remaining_time":0.4218530186},
{"learn":[4.133773523],"iteration":412,"passed_time":0.2970730813,"remaining_time":0.4222322003},
{"learn":[4.131363444],"iteration":413,"passed_time":0.2981577716,"remaining_time":0.4220300825},
{"learn":[4.130228592],"iteration":414,"passed_time":0.2985775725,"remaining_time":0.4208864576},
{"learn":[4.12884186],"iteration":415,"passed_time":0.298985372,"remaining_time":0.4197294645},
{"learn":[4.12413494],"iteration":416,"passed_time":0.2994241468,"remaining_time":0.4186193708},
{"learn":[4.119422508],"iteration":417,"passed_time":0.3003130322,"remaining_time":0.418139198},
{"learn":[4.117038244],"iteration":418,"passed_time":0.300905492,"remaining_time":0.4172460402},
{"learn":[4.116067631],"iteration":419,"passed_time":0.3014627388,"remaining_time":0.4163056869},
{"learn":[4.110343455],"iteration":420,"passed_time":0.3021495373,"remaining_time":0.4155453257},
{"learn":[4.105604544],"iteration":421,"passed_time":0.3026979884,"remaining_time":0.4145958229},
{"learn":[4.103390131],"iteration":422,"passed_time":0.3032422018,"remaining_time":0.4136424361},
{"learn":[4.096724402],"iteration":423,"passed_time":0.3038366351,"remaining_time":0.4127592025},
{"learn":[4.093431279],"iteration":424,"passed_time":0.3043835034,"remaining_time":0.4118129751},
{"learn":[4.091412744],"iteration":425,"passed_time":0.3048069007,"remaining_time":0.4107022559},
{"learn":[4.091192901],"iteration":426,"passed_time":0.3052046222,"remaining_time":0.4095603009},
{"learn":[4.088994581],"iteration":427,"passed_time":0.3056510708,"remaining_time":0.408486945},
{"learn":[4.087845355],"iteration":428,"passed_time":0.3061103623,"remaining_time":0.4074336058},
{"learn":[4.083650279],"iteration":429,"passed_time":0.3065215078,"remaining_time":0.406319208},
{"learn":[4.079840652],"iteration":430,"passed_time":0.3070591996,"remaining_time":0.4053751382},
{"learn":[4.075707828],"iteration":431,"passed_time":0.3077353791,"remaining_time":0.4046150355},
{"learn":[4.071345409],"iteration":432,"passed_time":0.3084904197,"remaining_time":0.4039585865},
{"learn":[4.067460475],"iteration":433,"passed_time":0.3090906033,"remaining_time":0.4030997269},
{"learn":[4.064914749],"iteration":434,"passed_time":0.3097265008,"remaining_time":0.4022884435},
{"learn":[4.063823175],"iteration":435,"passed_time":0.3103522601,"remaining_time":0.4014648502},
{"learn":[4.058898471],"iteration":436,"passed_time":0.310976076,"remaining_time":0.4006396585},
{"learn":[4.054120355],"iteration":437,"passed_time":0.3115546108,"remaining_time":0.399757286},
{"learn":[4.052715901],"iteration":438,"passed_time":0.3128068754,"remaining_time":0.39973726},
{"learn":[4.052114167],"iteration":439,"passed_time":0.3134119177,"remaining_time":0.3988878953},
{"learn":[4.051377267],"iteration":440,"passed_time":0.313925246,"remaining_time":0.3979233843},
{"learn":[4.049275336],"iteration":441,"passed_time":0.3144511066,"remaining_time":0.3969767364},
{"learn":[4.047099198],"iteration":442,"passed_time":0.3149392498,"remaining_time":0.3959845646},
{"learn":[4.044348685],"iteration":443,"passed_time":0.3155475779,"remaining_time":0.3951451652},
{"learn":[4.042822379],"iteration":444,"passed_time":0.3163384326,"remaining_time":0.3945344496},
{"learn":[4.041258611],"iteration":445,"passed_time":0.3169136716,"remaining_time":0.3936550988},
{"learn":[4.040044254],"iteration":446,"passed_time":0.317541745,"remaining_time":0.392842472},
{"learn":[4.036860137],"iteration":447,"passed_time":0.3180156527,"remaining_time":0.391840715},
{"learn":[4.036372284],"iteration":448,"passed_time":0.318436726,"remaining_time":0.3907764722},
{"learn":[4.03368231],"iteration":449,"passed_time":0.3188439844,"remaining_time":0.3896982032},
{"learn":[4.032439519],"iteration":450,"passed_time":0.3194317057,"remaining_time":0.3888425864},
{"learn":[4.032008634],"iteration":451,"passed_time":0.319927713,"remaining_time":0.3878769618},
{"learn":[4.030034932],"iteration":452,"passed_time":0.3204087835,"remaining_time":0.3868953743},
{"learn":[4.028173412],"iteration":453,"passed_time":0.3212001186,"remaining_time":0.3862891295},
{"learn":[4.023806097],"iteration":454,"passed_time":0.3218077756,"remaining_time":0.3854620609},
{"learn":[4.020239186],"iteration":455,"passed_time":0.3223771541,"remaining_time":0.3845902891},
{"learn":[4.017384838],"iteration":456,"passed_time":0.3235028677,"remaining_time":0.3843808691},
{"learn":[4.016468229],"iteration":457,"passed_time":0.3241790072,"remaining_time":0.383635419},
{"learn":[4.014530169],"iteration":458,"passed_time":0.324786033,"remaining_time":0.3828088102},
{"learn":[4.012884822],"iteration":459,"passed_time":0.3252824209,"remaining_time":0.3818532768},
{"learn":[4.008924707],"iteration":460,"passed_time":0.3258724421,"remaining_time":0.3810092111},
{"learn":[4.008286778],"iteration":461,"passed_time":0.3264154735,"remaining_time":0.3801115254},
{"learn":[4.006444202],"iteration":462,"passed_time":0.3269301942,"remaining_time":0.3791825362},
{"learn":[4.003284363],"iteration":463,"passed_time":0.3273818521,"remaining_time":0.3781824843},
{"learn":[3.999811484],"iteration":464,"passed_time":0.3278127328,"remaining_time":0.3771608862},
{"learn":[3.997483319],"iteration":465,"passed_time":0.328266214,"remaining_time":0.3761677216},
{"learn":[3.99708333],"iteration":466,"passed_time":0.3288974532,"remaining_time":0.3753797485},
{"learn":[3.995860263],"iteration":467,"passed_time":0.3293998118,"remaining_time":0.3744459399},
{"learn":[3.994131111],"iteration":468,"passed_time":0.3299202427,"remaining_time":0.3735344326},
{"learn":[3.993125499],"iteration":469,"passed_time":0.3303110217,"remaining_time":0.3724783862},
{"learn":[3.992954084],"iteration":470,"passed_time":0.3307005485,"remaining_time":0.3714237583},
{"learn":[3.990635743],"iteration":471,"passed_time":0.3311792748,"remaining_time":0.3704717311},
{"learn":[3.986678254],"iteration":472,"passed_time":0.3316625593,"remaining_time":0.3695267838},
{"learn":[3.986393291],"iteration":473,"passed_time":0.3322553797,"remaining_time":0.368705337},
{"learn":[3.986152671],"iteration":474,"passed_time":0.332768207,"remaining_time":0.3677964394},
{"learn":[3.985596662],"iteration":475,"passed_time":0.3333041858,"remaining_time":0.3669146919},
{"learn":[3.983853457],"iteration":476,"passed_time":0.3338103913,"remaining_time":0.3660017498},
{"learn":[3.983263928],"iteration":477,"passed_time":0.3344240189,"remaining_time":0.3652078198},
{"learn":[3.980067202],"iteration":478,"passed_time":0.3350259657,"remaining_time":0.3644019376},
{"learn":[3.978115407],"iteration":479,"passed_time":0.3359124714,"remaining_time":0.3639051774},
{"learn":[3.972661644],"iteration":480,"passed_time":0.3364861175,"remaining_time":0.3630692204},
{"learn":[3.969938254],"iteration":481,"passed_time":0.3370995548,"remaining_time":0.3622771149},
{"learn":[3.968211434],"iteration":482,"passed_time":0.3377479146,"remaining_time":0.3615231301},
{"learn":[3.966113368],"iteration":483,"passed_time":0.3382016362,"remaining_time":0.360562075},
{"learn":[3.962246044],"iteration":484,"passed_time":0.3389967986,"remaining_time":0.3599656727},
{"learn":[3.961319703],"iteration":485,"passed_time":0.3396517802,"remaining_time":0.3592201955},
{"learn":[3.96078191],"iteration":486,"passed_time":0.3402686536,"remaining_time":0.3584349472},
{"learn":[3.958913633],"iteration":487,"passed_time":0.3408183569,"remaining_time":0.3575799154},
{"learn":[3.957428286],"iteration":488,"passed_time":0.341320435,"remaining_time":0.3566763646},
{"learn":[3.952641965],"iteration":489,"passed_time":0.3418541998,"remaining_time":0.3558074324},
{"learn":[3.951486786],"iteration":490,"passed_time":0.3425176912,"remaining_time":0.3550743479},
{"learn":[3.94938344],"iteration":491,"passed_time":0.3429923202,"remaining_time":0.354146542},
{"learn":[3.947297924],"iteration":492,"passed_time":0.343476897,"remaining_time":0.3532308049},
{"learn":[3.946284886],"iteration":493,"passed_time":0.3440102411,"remaining_time":0.3523667651},
{"learn":[3.943288204],"iteration":494,"passed_time":0.3444516506,"remaining_time":0.3514102699},
{"learn":[3.943076488],"iteration":495,"passed_time":0.3448876506,"remaining_time":0.3504503546},
{"learn":[3.942347078],"iteration":496,"passed_time":0.3454039942,"remaining_time":0.3495738613},
{"learn":[3.940251541],"iteration":497,"passed_time":0.3458939706,"remaining_time":0.3486722354},
{"learn":[3.939011019],"iteration":498,"passed_time":0.3464486729,"remaining_time":0.3478372447},
{"learn":[3.938760512],"iteration":499,"passed_time":0.346963073,"remaining_time":0.346963073},
{"learn":[3.934522727],"iteration":500,"passed_time":0.3474241177,"remaining_time":0.3460371951},
{"learn":[3.930091193],"iteration":501,"passed_time":0.3479098065,"remaining_time":0.3451376168},
{"learn":[3.927671752],"iteration":502,"passed_time":0.3483683367,"remaining_time":0.3442128496},
{"learn":[3.927280041],"iteration":503,"passed_time":0.3492872204,"remaining_time":0.3437429788},
{"learn":[3.925987561],"iteration":504,"passed_time":0.3500551841,"remaining_time":0.3431233983},
{"learn":[3.921645957],"iteration":505,"passed_time":0.3509195402,"remaining_time":0.3425973377},
{"learn":[3.920333743],"iteration":506,"passed_time":0.3516475024,"remaining_time":0.3419373149},
{"learn":[3.918659461],"iteration":507,"passed_time":0.3522125431,"remaining_time":0.3411192346},
{"learn":[3.916124385],"iteration":508,"passed_time":0.3527153926,"remaining_time":0.3402421567},
{"learn":[3.913849268],"iteration":509,"passed_time":0.3531851328,"remaining_time":0.3393347355},
{"learn":[3.912826119],"iteration":510,"passed_time":0.3536950449,"remaining_time":0.3384674696},
{"learn":[3.910034145],"iteration":511,"passed_time":0.354123321,"remaining_time":0.3375237904},
{"learn":[3.90792379],"iteration":512,"passed_time":0.3547560028,"remaining_time":0.3367761664},
{"learn":[3.907823851],"iteration":513,"passed_time":0.355409682,"remaining_time":0.3360488433},
{"learn":[3.904527401],"iteration":514,"passed_time":0.3560361526,"remaining_time":0.3352961826},
{"learn":[3.903378283],"iteration":515,"passed_time":0.3566941997,"remaining_time":0.3345736292},
{"learn":[3.902170135],"iteration":516,"passed_time":0.3572445542,"remaining_time":0.333750715},
{"learn":[3.899435429],"iteration":517,"passed_time":0.3579374937,"remaining_time":0.3330615289},
{"learn":[3.897497505],"iteration":518,"passed_time":0.3584157592,"remaining_time":0.3321733722},
{"learn":[3.896426119],"iteration":519,"passed_time":0.3590362792,"remaining_time":0.3314181039},
{"learn":[3.896044669],"iteration":520,"passed_time":0.3595470629,"remaining_time":0.3305624628},
{"learn":[3.892795942],"iteration":521,"passed_time":0.3598985416,"remaining_time":0.329562266},
{"learn":[3.892413888],"iteration":522,"passed_time":0.3603740822,"remaining_time":0.3286777002},
{"learn":[3.891738985],"iteration":523,"passed_time":0.3607976799,"remaining_time":0.3277475108},
{"learn":[3.88822057],"iteration":524,"passed_time":0.3613001688,"remaining_time":0.3268906289},
{"learn":[3.883837053],"iteration":525,"passed_time":0.3617248484,"remaining_time":0.3259649775},
{"learn":[3.881769742],"iteration":526,"passed_time":0.3622442174,"remaining_time":0.3251262141},
{"learn":[3.880356898],"iteration":527,"passed_time":0.3627647185,"remaining_time":0.3242896726},
{"learn":[3.879250273],"iteration":528,"passed_time":0.3633700166,"remaining_time":0.3235298258},
{"learn":[3.877174493],"iteration":529,"passed_time":0.3644017868,"remaining_time":0.3231487544},
{"learn":[3.875854201],"iteration":530,"passed_time":0.3661328132,"remaining_time":0.3233828426},
{"learn":[3.873189396],"iteration":531,"passed_time":0.3675060797,"remaining_time":0.323294822},
{"learn":[3.871583368],"iteration":532,"passed_time":0.3680891427,"remaining_time":0.3225096241},
{"learn":[3.869622679],"iteration":533,"passed_time":0.3686857699,"remaining_time":0.3217370202},
{"learn":[3.866860164],"iteration":534,"passed_time":0.3691301648,"remaining_time":0.3208327601},
{"learn":[3.864498444],"iteration":535,"passed_time":0.3696509364,"remaining_time":0.319996333},
{"learn":[3.861416322],"iteration":536,"passed_time":0.3701837094,"remaining_time":0.3191714291},
{"learn":[3.860265769],"iteration":537,"passed_time":0.3707389626,"remaining_time":0.3183669158},
{"learn":[3.859328725],"iteration":538,"passed_time":0.3713723756,"remaining_time":0.3176301765},
{"learn":[3.858521278],"iteration":539,"passed_time":0.3718455821,"remaining_time":0.3167573477},
{"learn":[3.85599111],"iteration":540,"passed_time":0.3724440726,"remaining_time":0.3159922908},
{"learn":[3.852379816],"iteration":541,"passed_time":0.3730063083,"remaining_time":0.3151972126},
{"learn":[3.851327537],"iteration":542,"passed_time":0.3734854554,"remaining_time":0.3143330629},
{"learn":[3.847854898],"iteration":543,"passed_time":0.3739884151,"remaining_time":0.3134902891},
{"learn":[3.847083414],"iteration":544,"passed_time":0.3747674933,"remaining_time":0.3128792834},
{"learn":[3.845397429],"iteration":545,"passed_time":0.3752547148,"remaining_time":0.3120249827},
{"learn":[3.841933528],"iteration":546,"passed_time":0.3759185631,"remaining_time":0.3113182981},
{"learn":[3.840996474],"iteration":547,"passed_time":0.376541878,"remaining_time":0.3105783374},
{"learn":[3.838355966],"iteration":548,"passed_time":0.377480121,"remaining_time":0.3100975128},
{"learn":[3.83342799],"iteration":549,"passed_time":0.3792680137,"remaining_time":0.310310193},
{"learn":[3.828161535],"iteration":550,"passed_time":0.3798675461,"remaining_time":0.3095472381},
{"learn":[3.823502399],"iteration":551,"passed_time":0.3804015814,"remaining_time":0.3087317182},
{"learn":[3.820068862],"iteration":552,"passed_time":0.3809403251,"remaining_time":0.3079210223},
{"learn":[3.817951642],"iteration":553,"passed_time":0.3814195924,"remaining_time":0.3070634264},
{"learn":[3.815785958],"iteration":554,"passed_time":0.3819783118,"remaining_time":0.3062708986},
{"learn":[3.81503012],"iteration":555,"passed_time":0.382494435,"remaining_time":0.3054451963},
{"learn":[3.813529315],"iteration":556,"passed_time":0.3830338499,"remaining_time":0.3046391302},
{"learn":[3.808881326],"iteration":557,"passed_time":0.3835816298,"remaining_time":0.3038406458},
{"learn":[3.808740434],"iteration":558,"passed_time":0.3840785787,"remaining_time":0.3030029574},
{"learn":[3.80714352],"iteration":559,"passed_time":0.3848363041,"remaining_time":0.3023713818},
{"learn":[3.80573346],"iteration":560,"passed_time":0.385293562,"remaining_time":0.3015042312},
{"learn":[3.803370052],"iteration":561,"passed_time":0.3857388786,"remaining_time":0.3006292328},
{"learn":[3.803215211],"iteration":562,"passed_time":0.3862694376,"remaining_time":0.2998219258},
{"learn":[3.801309667],"iteration":563,"passed_time":0.3868186701,"remaining_time":0.2990300357},
{"learn":[3.800003847],"iteration":564,"passed_time":0.3872485891,"remaining_time":0.2981471438},
{"learn":[3.798026138],"iteration":565,"passed_time":0.3877637606,"remaining_time":0.2973312228},
{"learn":[3.794745847],"iteration":566,"passed_time":0.3883043777,"remaining_time":0.2965357946},
{"learn":[3.794312041],"iteration":567,"passed_time":0.3888859279,"remaining_time":0.2957723959},
{"learn":[3.792205926],"iteration":568,"passed_time":0.3893476438,"remaining_time":0.2949188655},
{"learn":[3.788991061],"iteration":569,"passed_time":0.389929124,"remaining_time":0.2941570584},
{"learn":[3.787391572],"iteration":570,"passed_time":0.3905515732,"remaining_time":0.2934266635},
{"learn":[3.7826445],"iteration":571,"passed_time":0.3920572665,"remaining_time":0.2933575351},
{"learn":[3.781700331],"iteration":572,"passed_time":0.3931646373,"remaining_time":0.2929865622},
{"learn":[3.780045374],"iteration":573,"passed_time":0.3950630774,"remaining_time":0.2932001237},
{"learn":[3.775462644],"iteration":574,"passed_time":0.3956200838,"remaining_time":0.2924148445},
{"learn":[3.773711943],"iteration":575,"passed_time":0.3963175414,"remaining_time":0.2917337457},
{"learn":[3.772415806],"iteration":576,"passed_time":0.3969220226,"remaining_time":0.2909844291},
{"learn":[3.770170875],"iteration":577,"passed_time":0.3974269959,"remaining_time":0.2901629624},
{"learn":[3.765166479],"iteration":578,"passed_time":0.3979253674,"remaining_time":0.2893377887},
{"learn":[3.763976102],"iteration":579,"passed_time":0.3985202715,"remaining_time":0.2885836449},
{"learn":[3.760761708],"iteration":580,"passed_time":0.3994887647,"remaining_time":0.2880994706},
{"learn":[3.758155662],"iteration":581,"passed_time":0.4001394286,"remaining_time":0.2873853628},
{"learn":[3.756844548],"iteration":582,"passed_time":0.4006411861,"remaining_time":0.286564965},
{"learn":[3.753098923],"iteration":583,"passed_time":0.4013331038,"remaining_time":0.2858811151},
{"learn":[3.751618946],"iteration":584,"passed_time":0.4019534635,"remaining_time":0.2851464741},
{"learn":[3.751398464],"iteration":585,"passed_time":0.4025149078,"remaining_time":0.2843706004},
{"learn":[3.749920103],"iteration":586,"passed_time":0.402973458,"remaining_time":0.2835230633},
{"learn":[3.748237465],"iteration":587,"passed_time":0.4035125123,"remaining_time":0.2827332569},
{"learn":[3.746021536],"iteration":588,"passed_time":0.4040790657,"remaining_time":0.2819634907},
{"learn":[3.74417648],"iteration":589,"passed_time":0.4055578201,"remaining_time":0.2818283157},
{"learn":[3.738788389],"iteration":590,"passed_time":0.4072634411,"remaining_time":0.2818455963},
{"learn":[3.736021611],"iteration":591,"passed_time":0.4083984471,"remaining_time":0.2814637946},
{"learn":[3.734546151],"iteration":592,"passed_time":0.4090042307,"remaining_time":0.2807162258},
{"learn":[3.733527479],"iteration":593,"passed_time":0.409678738,"remaining_time":0.2800161071},
{"learn":[3.733026392],"iteration":594,"passed_time":0.410187438,"remaining_time":0.2792032141},
{"learn":[3.730314752],"iteration":595,"passed_time":0.4106784362,"remaining_time":0.2783793427},
{"learn":[3.727342596],"iteration":596,"passed_time":0.4110950915,"remaining_time":0.2775064018},
{"learn":[3.725459604],"iteration":597,"passed_time":0.4115238986,"remaining_time":0.2766431559},
{"learn":[3.723158842],"iteration":598,"passed_time":0.4120042779,"remaining_time":0.2758158855},
{"learn":[3.722362756],"iteration":599,"passed_time":0.4124050447,"remaining_time":0.2749366965},
{"learn":[3.721443615],"iteration":600,"passed_time":0.4128294739,"remaining_time":0.2740748088},
{"learn":[3.720743486],"iteration":601,"passed_time":0.4134616948,"remaining_time":0.2733517517},
{"learn":[3.720215334],"iteration":602,"passed_time":0.413931916,"remaining_time":0.2725223394},
{"learn":[3.719436563],"iteration":603,"passed_time":0.4144795556,"remaining_time":0.2717448742},
{"learn":[3.715046574],"iteration":604,"passed_time":0.4148761249,"remaining_time":0.2708695361},
{"learn":[3.71443396],"iteration":605,"passed_time":0.4153211009,"remaining_time":0.2700272504},
{"learn":[3.712938941],"iteration":606,"passed_time":0.4157604468,"remaining_time":0.2691826286},
{"learn":[3.712814764],"iteration":607,"passed_time":0.4162014957,"remaining_time":0.268340438},
{"learn":[3.71235348],"iteration":608,"passed_time":0.4166450191,"remaining_time":0.2675011535},
{"learn":[3.711223749],"iteration":609,"passed_time":0.4170942126,"remaining_time":0.2666667916},
{"learn":[3.710755648],"iteration":610,"passed_time":0.4174709264,"remaining_time":0.2657875456},
{"learn":[3.708668039],"iteration":611,"passed_time":0.4178665341,"remaining_time":0.2649219203},
{"learn":[3.705623591],"iteration":612,"passed_time":0.4184385874,"remaining_time":0.2641692224},
{"learn":[3.704045802],"iteration":613,"passed_time":0.4190999704,"remaining_time":0.2634732713},
{"learn":[3.699915209],"iteration":614,"passed_time":0.4196629575,"remaining_time":0.2627158352},
{"learn":[3.696182221],"iteration":615,"passed_time":0.4205620658,"remaining_time":0.2621685605},
{"learn":[3.694263278],"iteration":616,"passed_time":0.4214203102,"remaining_time":0.2615947793},
{"learn":[3.693810229],"iteration":617,"passed_time":0.421947393,"remaining_time":0.2608153789},
{"learn":[3.690900932],"iteration":618,"passed_time":0.4224313187,"remaining_time":0.2600102301},
{"learn":[3.688020895],"iteration":619,"passed_time":0.4230249605,"remaining_time":0.2592733629},
{"learn":[3.685491894],"iteration":620,"passed_time":0.4235269986,"remaining_time":0.2584810507},
{"learn":[3.684328128],"iteration":621,"passed_time":0.4240413687,"remaining_time":0.2576971662},
{"learn":[3.680640153],"iteration":622,"passed_time":0.4245298925,"remaining_time":0.2568985064},
{"learn":[3.678932783],"iteration":623,"passed_time":0.4249823018,"remaining_time":0.2560790793},
{"learn":[3.674167041],"iteration":624,"passed_time":0.4254834783,"remaining_time":0.255290087},
{"learn":[3.672200976],"iteration":625,"passed_time":0.4259189472,"remaining_time":0.2544627576},
{"learn":[3.670606604],"iteration":626,"passed_time":0.4264297609,"remaining_time":0.2536815005},
{"learn":[3.665506042],"iteration":627,"passed_time":0.4268829716,"remaining_time":0.2528669832},
{"learn":[3.664214007],"iteration":628,"passed_time":0.4275402574,"remaining_time":0.2521739833},
{"learn":[3.66261643],"iteration":629,"passed_time":0.4280767771,"remaining_time":0.2514101707},
{"learn":[3.662118449],"iteration":630,"passed_time":0.4287684643,"remaining_time":0.2507378183},
{"learn":[3.660871366],"iteration":631,"passed_time":0.4292605045,"remaining_time":0.2499491545},
{"learn":[3.656695243],"iteration":632,"passed_time":0.42977251,"remaining_time":0.2491730034},
{"learn":[3.654497801],"iteration":633,"passed_time":0.430216394,"remaining_time":0.2483583599},
{"learn":[3.654189134],"iteration":634,"passed_time":0.4308970218,"remaining_time":0.2476809653},
{"learn":[3.653957699],"iteration":635,"passed_time":0.4314442808,"remaining_time":0.2469272299},
{"learn":[3.651920725],"iteration":636,"passed_time":0.4317868836,"remaining_time":0.2460575177},
{"learn":[3.65106705],"iteration":637,"passed_time":0.4322788136,"remaining_time":0.2452741857},
{"learn":[3.650612844],"iteration":638,"passed_time":0.4326923032,"remaining_time":0.2444474514},
{"learn":[3.649884732],"iteration":639,"passed_time":0.4330659816,"remaining_time":0.2435996147},
{"learn":[3.646276182],"iteration":640,"passed_time":0.4334706555,"remaining_time":0.2427706167},
{"learn":[3.645808194],"iteration":641,"passed_time":0.4339197488,"remaining_time":0.2419677104},
{"learn":[3.645042989],"iteration":642,"passed_time":0.4346696502,"remaining_time":0.2413329162},
{"learn":[3.639864499],"iteration":643,"passed_time":0.4351946293,"remaining_time":0.2405734286},
{"learn":[3.637318478],"iteration":644,"passed_time":0.4358927781,"remaining_time":0.2399099786},
{"learn":[3.636344905],"iteration":645,"passed_time":0.4364342066,"remaining_time":0.2391605405},
{"learn":[3.634754643],"iteration":646,"passed_time":0.4369255956,"remaining_time":0.238384444},
{"learn":[3.630724975],"iteration":647,"passed_time":0.4375154707,"remaining_time":0.2376627248},
{"learn":[3.629408252],"iteration":648,"passed_time":0.438060666,"remaining_time":0.2369172477},
{"learn":[3.62790646],"iteration":649,"passed_time":0.4384512947,"remaining_time":0.2360891587},
{"learn":[3.627388973],"iteration":650,"passed_time":0.438896471,"remaining_time":0.2352916565},
{"learn":[3.625163557],"iteration":651,"passed_time":0.4392943828,"remaining_time":0.234470008},
{"learn":[3.623701985],"iteration":652,"passed_time":0.439882961,"remaining_time":0.2337509762},
{"learn":[3.622342639],"iteration":653,"passed_time":0.4403714047,"remaining_time":0.232979367},
{"learn":[3.621130639],"iteration":654,"passed_time":0.4407524163,"remaining_time":0.232152036},
{"learn":[3.619125665],"iteration":655,"passed_time":0.4412310825,"remaining_time":0.231377275},
{"learn":[3.618878783],"iteration":656,"passed_time":0.441717753,"remaining_time":0.230607594},
{"learn":[3.616207429],"iteration":657,"passed_time":0.4422712531,"remaining_time":0.2298735085},
{"learn":[3.61206486],"iteration":658,"passed_time":0.4427837498,"remaining_time":0.2291187537},
{"learn":[3.611955873],"iteration":659,"passed_time":0.443378634,"remaining_time":0.2284071751},
{"learn":[3.610713743],"iteration":660,"passed_time":0.4438559678,"remaining_time":0.2276356628},
{"learn":[3.610044025],"iteration":661,"passed_time":0.4453571773,"remaining_time":0.2273878035},
{"learn":[3.607342669],"iteration":662,"passed_time":0.4462543325,"remaining_time":0.2268291253},
{"learn":[3.602510618],"iteration":663,"passed_time":0.446885191,"remaining_time":0.226134675},
{"learn":[3.600492392],"iteration":664,"passed_time":0.4473593892,"remaining_time":0.2253614968},
{"learn":[3.597171065],"iteration":665,"passed_time":0.4479368422,"remaining_time":0.2246409989},
{"learn":[3.594358798],"iteration":666,"passed_time":0.4485674702,"remaining_time":0.2239474776},
{"learn":[3.593945251],"iteration":667,"passed_time":0.4492316182,"remaining_time":0.2232708043},
{"learn":[3.593607748],"iteration":668,"passed_time":0.4498126976,"remaining_time":0.2225530686},
{"learn":[3.592238714],"iteration":669,"passed_time":0.4503517419,"remaining_time":0.221815037},
{"learn":[3.590144654],"iteration":670,"passed_time":0.4510643666,"remaining_time":0.2211627073},
{"learn":[3.587151536],"iteration":671,"passed_time":0.4520126983,"remaining_time":0.2206252456},
{"learn":[3.586070865],"iteration":672,"passed_time":0.4525400416,"remaining_time":0.2198820113},
{"learn":[3.585102746],"iteration":673,"passed_time":0.4530547523,"remaining_time":0.2191333075},
{"learn":[3.584362847],"iteration":674,"passed_time":0.4536253329,"remaining_time":0.2184121973},
{"learn":[3.581407561],"iteration":675,"passed_time":0.45445666,"remaining_time":0.2178165057},
{"learn":[3.57919422],"iteration":676,"passed_time":0.4551498099,"remaining_time":0.2171541929},
{"learn":[3.577632204],"iteration":677,"passed_time":0.4563966602,"remaining_time":0.216754756},
{"learn":[3.573911195],"iteration":678,"passed_time":0.456952244,"remaining_time":0.216026024},
{"learn":[3.573408216],"iteration":679,"passed_time":0.4578814315,"remaining_time":0.2154736148},
{"learn":[3.571076482],"iteration":680,"passed_time":0.4585870537,"remaining_time":0.2148153746},
{"learn":[3.568177107],"iteration":681,"passed_time":0.4590309878,"remaining_time":0.2140349767},
{"learn":[3.564824621],"iteration":682,"passed_time":0.4595027216,"remaining_time":0.2132684667},
{"learn":[3.562475026],"iteration":683,"passed_time":0.4599691059,"remaining_time":0.2125003472},
{"learn":[3.561226889],"iteration":684,"passed_time":0.4605154932,"remaining_time":0.2117698983},
{"learn":[3.559383467],"iteration":685,"passed_time":0.461002875,"remaining_time":0.2110129778},
{"learn":[3.555209766],"iteration":686,"passed_time":0.4615239271,"remaining_time":0.2102721822},
{"learn":[3.55345383],"iteration":687,"passed_time":0.4621253329,"remaining_time":0.2095684649},
{"learn":[3.552300968],"iteration":688,"passed_time":0.462663235,"remaining_time":0.2088363804},
{"learn":[3.551253986],"iteration":689,"passed_time":0.4638767958,"remaining_time":0.2084084155},
{"learn":[3.549807725],"iteration":690,"passed_time":0.4644471661,"remaining_time":0.2076905562},
{"learn":[3.547992926],"iteration":691,"passed_time":0.4649734475,"remaining_time":0.2069534997},
{"learn":[3.545438607],"iteration":692,"passed_time":0.465522139,"remaining_time":0.2062269793},
{"learn":[3.543313763],"iteration":693,"passed_time":0.4660954845,"remaining_time":0.2055118419},
{"learn":[3.542962896],"iteration":694,"passed_time":0.466859952,"remaining_time":0.2048809861},
{"learn":[3.539800465],"iteration":695,"passed_time":0.4674898588,"remaining_time":0.2041909728},
{"learn":[3.53953187],"iteration":696,"passed_time":0.4682574518,"remaining_time":0.2035609869},
{"learn":[3.536332425],"iteration":697,"passed_time":0.4687431005,"remaining_time":0.2028086194},
{"learn":[3.534993327],"iteration":698,"passed_time":0.4693275159,"remaining_time":0.2020995455},
{"learn":[3.531637011],"iteration":699,"passed_time":0.4700915372,"remaining_time":0.2014678016},
{"learn":[3.531040284],"iteration":700,"passed_time":0.4721274489,"remaining_time":0.2013781844},
{"learn":[3.529973872],"iteration":701,"passed_time":0.4727971769,"remaining_time":0.2007030751},
{"learn":[3.527325183],"iteration":702,"passed_time":0.4740396695,"remaining_time":0.2002699599},
{"learn":[3.527200815],"iteration":703,"passed_time":0.4746312877,"remaining_time":0.1995608823},
{"learn":[3.523459911],"iteration":704,"passed_time":0.4759439157,"remaining_time":0.1991538371},
{"learn":[3.522729934],"iteration":705,"passed_time":0.4770179469,"remaining_time":0.1986448674},
{"learn":[3.522260582],"iteration":706,"passed_time":0.4777411906,"remaining_time":0.1979889234},
{"learn":[3.518641591],"iteration":707,"passed_time":0.4784744122,"remaining_time":0.1973369045},
{"learn":[3.516856405],"iteration":708,"passed_time":0.4790869579,"remaining_time":0.1966351266},
{"learn":[3.515083413],"iteration":709,"passed_time":0.4797917085,"remaining_time":0.1959712612},
{"learn":[3.514671214],"iteration":710,"passed_time":0.480678034,"remaining_time":0.1953810855},
{"learn":[3.512617621],"iteration":711,"passed_time":0.4814146516,"remaining_time":0.194729522},
{"learn":[3.510747971],"iteration":712,"passed_time":0.481962201,"remaining_time":0.1940016153},
{"learn":[3.508149266],"iteration":713,"passed_time":0.4825929293,"remaining_time":0.1933075319},
{"learn":[3.504557165],"iteration":714,"passed_time":0.4832020589,"remaining_time":0.1926050165},
{"learn":[3.501367208],"iteration":715,"passed_time":0.4843553626,"remaining_time":0.1921186075},
{"learn":[3.497593362],"iteration":716,"passed_time":0.4855109397,"remaining_time":0.1916312356},
{"learn":[3.496291169],"iteration":717,"passed_time":0.4862433498,"remaining_time":0.1909758003},
{"learn":[3.49330374],"iteration":718,"passed_time":0.4868629982,"remaining_time":0.1902760814},
{"learn":[3.490044385],"iteration":719,"passed_time":0.4875495363,"remaining_time":0.1896025974},
{"learn":[3.488891789],"iteration":720,"passed_time":0.4882646046,"remaining_time":0.1889401175},
{"learn":[3.486869081],"iteration":721,"passed_time":0.4894054553,"remaining_time":0.1884414357},
{"learn":[3.486303638],"iteration":722,"passed_time":0.4933673923,"remaining_time":0.1890218087},
{"learn":[3.486035862],"iteration":723,"passed_time":0.4941507636,"remaining_time":0.1883779154},
{"learn":[3.482668951],"iteration":724,"passed_time":0.4947842668,"remaining_time":0.1876767908},
{"learn":[3.47820549],"iteration":725,"passed_time":0.4954399396,"remaining_time":0.1869842196},
{"learn":[3.474392283],"iteration":726,"passed_time":0.4962183921,"remaining_time":0.1863378556},
{"learn":[3.472268163],"iteration":727,"passed_time":0.4968977273,"remaining_time":0.1856540959},
{"learn":[3.471209164],"iteration":728,"passed_time":0.4974310412,"remaining_time":0.1849160661},
{"learn":[3.470049971],"iteration":729,"passed_time":0.4980227697,"remaining_time":0.1842002025},
{"learn":[3.469078654],"iteration":730,"passed_time":0.4990023126,"remaining_time":0.18362739},
{"learn":[3.468643292],"iteration":731,"passed_time":0.4996993988,"remaining_time":0.1829500531},
{"learn":[3.468134848],"iteration":732,"passed_time":0.5005259932,"remaining_time":0.1823198365},
{"learn":[3.467820182],"iteration":733,"passed_time":0.5016726893,"remaining_time":0.181805089},
{"learn":[3.465776156],"iteration":734,"passed_time":0.5023113417,"remaining_time":0.1811054497},
{"learn":[3.463037608],"iteration":735,"passed_time":0.502896248,"remaining_time":0.1803866977},
{"learn":[3.45965637],"iteration":736,"passed_time":0.5038095266,"remaining_time":0.1797854892},
{"learn":[3.457275091],"iteration":737,"passed_time":0.5044327915,"remaining_time":0.1790804761},
{"learn":[3.455522955],"iteration":738,"passed_time":0.5052200193,"remaining_time":0.1784335927},
{"learn":[3.451270508],"iteration":739,"passed_time":0.5065739724,"remaining_time":0.1779854498},
{"learn":[3.450978947],"iteration":740,"passed_time":0.5074625218,"remaining_time":0.1773721905},
{"learn":[3.450608492],"iteration":741,"passed_time":0.50816031,"remaining_time":0.1766918598},
{"learn":[3.448122004],"iteration":742,"passed_time":0.5087894954,"remaining_time":0.1759877528},
{"learn":[3.445646714],"iteration":743,"passed_time":0.5093736704,"remaining_time":0.1752683597},
{"learn":[3.44411263],"iteration":744,"passed_time":0.5099099296,"remaining_time":0.1745329289},
{"learn":[3.443264164],"iteration":745,"passed_time":0.510546899,"remaining_time":0.1738323222},
{"learn":[3.439521363],"iteration":746,"passed_time":0.5111323963,"remaining_time":0.1731144528},
{"learn":[3.436809225],"iteration":747,"passed_time":0.5118744838,"remaining_time":0.1724496924},
{"learn":[3.435509465],"iteration":748,"passed_time":0.5125339835,"remaining_time":0.1717570492},
{"learn":[3.434450277],"iteration":749,"passed_time":0.513154253,"remaining_time":0.1710514177},
{"learn":[3.431786753],"iteration":750,"passed_time":0.5137907014,"remaining_time":0.1703513777},
{"learn":[3.430150302],"iteration":751,"passed_time":0.5144336916,"remaining_time":0.1696536642},
{"learn":[3.42696281],"iteration":752,"passed_time":0.5155482144,"remaining_time":0.1691107689},
{"learn":[3.426870334],"iteration":753,"passed_time":0.5169957796,"remaining_time":0.1686750156},
{"learn":[3.425200309],"iteration":754,"passed_time":0.5175940197,"remaining_time":0.1679609733},
{"learn":[3.423383783],"iteration":755,"passed_time":0.5183655336,"remaining_time":0.1673031616},
{"learn":[3.422752979],"iteration":756,"passed_time":0.5207911529,"remaining_time":0.167176024},
{"learn":[3.420845924],"iteration":757,"passed_time":0.5215490385,"remaining_time":0.1665103791},
{"learn":[3.418917862],"iteration":758,"passed_time":0.5227111781,"remaining_time":0.165972851},
{"learn":[3.417095735],"iteration":759,"passed_time":0.5234631833,"remaining_time":0.1653041631},
{"learn":[3.414391848],"iteration":760,"passed_time":0.5240791751,"remaining_time":0.1645925399},
{"learn":[3.41426711],"iteration":761,"passed_time":0.5247867601,"remaining_time":0.1639097755},
{"learn":[3.411976013],"iteration":762,"passed_time":0.5261428859,"remaining_time":0.1634283931},
{"learn":[3.408614844],"iteration":763,"passed_time":0.5268400429,"remaining_time":0.1627411651},
{"learn":[3.407906721],"iteration":764,"passed_time":0.5275316801,"remaining_time":0.1620522155},
{"learn":[3.407494015],"iteration":765,"passed_time":0.5280991051,"remaining_time":0.1613253141},
{"learn":[3.406287128],"iteration":766,"passed_time":0.5288121305,"remaining_time":0.1606430592},
{"learn":[3.404600442],"iteration":767,"passed_time":0.5295347131,"remaining_time":0.1599636112},
{"learn":[3.404012662],"iteration":768,"passed_time":0.5300475704,"remaining_time":0.1592210517},
{"learn":[3.400398762],"iteration":769,"passed_time":0.5305635634,"remaining_time":0.1584800254},
{"learn":[3.399737714],"iteration":770,"passed_time":0.5311388525,"remaining_time":0.1577571948},
{"learn":[3.399185251],"iteration":771,"passed_time":0.5316890467,"remaining_time":0.157027335},
{"learn":[3.397245411],"iteration":772,"passed_time":0.5323969529,"remaining_time":0.156344254},
{"learn":[3.396229831],"iteration":773,"passed_time":0.5329817791,"remaining_time":0.1556251706},
{"learn":[3.394002836],"iteration":774,"passed_time":0.5337320769,"remaining_time":0.154954474},
{"learn":[3.389617243],"iteration":775,"passed_time":0.5349631032,"remaining_time":0.1544223391},
{"learn":[3.385426488],"iteration":776,"passed_time":0.5357563622,"remaining_time":0.1537627655},
{"learn":[3.385072258],"iteration":777,"passed_time":0.5364290855,"remaining_time":0.1530684537},
{"learn":[3.383842366],"iteration":778,"passed_time":0.5373807474,"remaining_time":0.1524533314},
{"learn":[3.380110746],"iteration":779,"passed_time":0.5379865611,"remaining_time":0.1517397993},
{"learn":[3.378595218],"iteration":780,"passed_time":0.5386613281,"remaining_time":0.1510458782},
{"learn":[3.377371219],"iteration":781,"passed_time":0.5393060413,"remaining_time":0.1503436279},
{"learn":[3.375814782],"iteration":782,"passed_time":0.5399321713,"remaining_time":0.1496363744},
{"learn":[3.374195887],"iteration":783,"passed_time":0.5404783784,"remaining_time":0.1489073083},
{"learn":[3.373704309],"iteration":784,"passed_time":0.5413392282,"remaining_time":0.1482648842},
{"learn":[3.372971757],"iteration":785,"passed_time":0.5419726913,"remaining_time":0.1475599948},
{"learn":[3.371565136],"iteration":786,"passed_time":0.542872571,"remaining_time":0.1469273922},
{"learn":[3.3700309],"iteration":787,"passed_time":0.5444757144,"remaining_time":0.146483314},
{"learn":[3.368186663],"iteration":788,"passed_time":0.5452365654,"remaining_time":0.145811046},
{"learn":[3.366710398],"iteration":789,"passed_time":0.5458651999,"remaining_time":0.1451034076},
{"learn":[3.364598042],"iteration":790,"passed_time":0.5466633376,"remaining_time":0.1444407554},
{"learn":[3.36348442],"iteration":791,"passed_time":0.5472965403,"remaining_time":0.1437344449},
{"learn":[3.362001759],"iteration":792,"passed_time":0.5481105317,"remaining_time":0.1430755108},
{"learn":[3.361580401],"iteration":793,"passed_time":0.5489942417,"remaining_time":0.1424342743},
{"learn":[3.359543675],"iteration":794,"passed_time":0.5500997191,"remaining_time":0.1418496131},
{"learn":[3.35766119],"iteration":795,"passed_time":0.5507187961,"remaining_time":0.1411389879},
{"learn":[3.354592969],"iteration":796,"passed_time":0.5516461453,"remaining_time":0.140507111},
{"learn":[3.350985986],"iteration":797,"passed_time":0.5523378827,"remaining_time":0.1398148525},
{"learn":[3.349589624],"iteration":798,"passed_time":0.5529907806,"remaining_time":0.1391128246},
{"learn":[3.349110856],"iteration":799,"passed_time":0.5542517361,"remaining_time":0.138562934},
{"learn":[3.345315441],"iteration":800,"passed_time":0.5553579549,"remaining_time":0.1379728252},
{"learn":[3.34397474],"iteration":801,"passed_time":0.5559449048,"remaining_time":0.1372532309},
{"learn":[3.343800902],"iteration":802,"passed_time":0.5564956399,"remaining_time":0.1365250823},
{"learn":[3.342329465],"iteration":803,"passed_time":0.5570649583,"remaining_time":0.1358019053},
{"learn":[3.34220347],"iteration":804,"passed_time":0.5580220904,"remaining_time":0.135173053},
{"learn":[3.341279219],"iteration":805,"passed_time":0.5586853468,"remaining_time":0.1344726517},
{"learn":[3.337329521],"iteration":806,"passed_time":0.5593868617,"remaining_time":0.1337814923},
{"learn":[3.336708453],"iteration":807,"passed_time":0.5601730333,"remaining_time":0.1331104238},
{"learn":[3.333252703],"iteration":808,"passed_time":0.5607781758,"remaining_time":0.1323963307},
{"learn":[3.332186769],"iteration":809,"passed_time":0.5613860832,"remaining_time":0.1316831553},
{"learn":[3.330594851],"iteration":810,"passed_time":0.5620535271,"remaining_time":0.1309841142},
{"learn":[3.327867442],"iteration":811,"passed_time":0.5639159385,"remaining_time":0.1305618183},
{"learn":[3.327563111],"iteration":812,"passed_time":0.5647856088,"remaining_time":0.129907637},
{"learn":[3.326308994],"iteration":813,"passed_time":0.565607519,"remaining_time":0.1292420129},
{"learn":[3.326249879],"iteration":814,"passed_time":0.5665464485,"remaining_time":0.1286025681},
{"learn":[3.322336238],"iteration":815,"passed_time":0.5671461512,"remaining_time":0.1278858968},
{"learn":[3.320491154],"iteration":816,"passed_time":0.5677619327,"remaining_time":0.1271731135},
{"learn":[3.320434271],"iteration":817,"passed_time":0.5686205085,"remaining_time":0.1265145875},
{"learn":[3.319609638],"iteration":818,"passed_time":0.5698703099,"remaining_time":0.1259420343},
{"learn":[3.316182682],"iteration":819,"passed_time":0.5705817024,"remaining_time":0.125249642},
{"learn":[3.313126612],"iteration":820,"passed_time":0.5711905816,"remaining_time":0.1245348527},
{"learn":[3.311222803],"iteration":821,"passed_time":0.571860009,"remaining_time":0.1238334326},
{"learn":[3.309627335],"iteration":822,"passed_time":0.5726202189,"remaining_time":0.1231516145},
{"learn":[3.307974895],"iteration":823,"passed_time":0.5732672462,"remaining_time":0.1224454312},
{"learn":[3.307321505],"iteration":824,"passed_time":0.5739731389,"remaining_time":0.121751878},
{"learn":[3.306759087],"iteration":825,"passed_time":0.5748105018,"remaining_time":0.1210859895},
{"learn":[3.30484037],"iteration":826,"passed_time":0.5754405588,"remaining_time":0.12037632},
{"learn":[3.30201994],"iteration":827,"passed_time":0.5761501169,"remaining_time":0.1196833576},
{"learn":[3.299302297],"iteration":828,"passed_time":0.5780996002,"remaining_time":0.1192461178},
{"learn":[3.298132671],"iteration":829,"passed_time":0.5794185745,"remaining_time":0.1186760936},
{"learn":[3.296976183],"iteration":830,"passed_time":0.5802377957,"remaining_time":0.1180026323},
{"learn":[3.293144745],"iteration":831,"passed_time":0.580847336,"remaining_time":0.1172864813},
{"learn":[3.290284404],"iteration":832,"passed_time":0.5815501632,"remaining_time":0.1165892884},
{"learn":[3.288285745],"iteration":833,"passed_time":0.5821017799,"remaining_time":0.115861985},
{"learn":[3.286662667],"iteration":834,"passed_time":0.5827088659,"remaining_time":0.1151460633},
{"learn":[3.285692682],"iteration":835,"passed_time":0.5831889847,"remaining_time":0.1144054946},
{"learn":[3.284565611],"iteration":836,"passed_time":0.5838551263,"remaining_time":0.1137017749},
{"learn":[3.283897383],"iteration":837,"passed_time":0.5843775207,"remaining_time":0.112970356},
{"learn":[3.280712855],"iteration":838,"passed_time":0.5849693093,"remaining_time":0.1122527518},
{"learn":[3.280468341],"iteration":839,"passed_time":0.5855989556,"remaining_time":0.1115426582},
{"learn":[3.277814895],"iteration":840,"passed_time":0.5862197661,"remaining_time":0.1108310854},
{"learn":[3.276316385],"iteration":841,"passed_time":0.5868901452,"remaining_time":0.1101290296},
{"learn":[3.27557063],"iteration":842,"passed_time":0.5876136093,"remaining_time":0.1094369355},
{"learn":[3.27499628],"iteration":843,"passed_time":0.5882022222,"remaining_time":0.108719842},
{"learn":[3.273569958],"iteration":844,"passed_time":0.5894815094,"remaining_time":0.1081297443},
{"learn":[3.269665595],"iteration":845,"passed_time":0.5901846372,"remaining_time":0.1074331373},
{"learn":[3.267984685],"iteration":846,"passed_time":0.5908478535,"remaining_time":0.1067293053},
{"learn":[3.267702508],"iteration":847,"passed_time":0.5917550663,"remaining_time":0.1060693043},
{"learn":[3.266671924],"iteration":848,"passed_time":0.5937848668,"remaining_time":0.1056083803},
{"learn":[3.265359825],"iteration":849,"passed_time":0.5943867935,"remaining_time":0.1048917871},
{"learn":[3.2618983],"iteration":850,"passed_time":0.5952177499,"remaining_time":0.1042155637},
{"learn":[3.260456253],"iteration":851,"passed_time":0.5959017233,"remaining_time":0.1035134449},
{"learn":[3.258389147],"iteration":852,"passed_time":0.5966424984,"remaining_time":0.1028211574},
{"learn":[3.258108469],"iteration":853,"passed_time":0.5972705719,"remaining_time":0.1021094889},
{"learn":[3.256424936],"iteration":854,"passed_time":0.5979160465,"remaining_time":0.1014009669},
{"learn":[3.254817983],"iteration":855,"passed_time":0.5984979474,"remaining_time":0.1006818977},
{"learn":[3.253898449],"iteration":856,"passed_time":0.5990945946,"remaining_time":0.09996560914},
{"learn":[3.253023652],"iteration":857,"passed_time":0.6031838243,"remaining_time":0.09982762594},
{"learn":[3.252845542],"iteration":858,"passed_time":0.6038487237,"remaining_time":0.0991183586},
{"learn":[3.252316026],"iteration":859,"passed_time":0.6045968018,"remaining_time":0.09842273518},
{"learn":[3.24975301],"iteration":860,"passed_time":0.6055957537,"remaining_time":0.09776749102},
{"learn":[3.249151075],"iteration":861,"passed_time":0.6061762821,"remaining_time":0.0970444628},
{"learn":[3.246257135],"iteration":862,"passed_time":0.6070909683,"remaining_time":0.09637481189},
{"learn":[3.243826471],"iteration":863,"passed_time":0.6083706366,"remaining_time":0.09576204464},
{"learn":[3.243190653],"iteration":864,"passed_time":0.6090958939,"remaining_time":0.09506120887},
{"learn":[3.24008797],"iteration":865,"passed_time":0.6097379724,"remaining_time":0.09434744608},
{"learn":[3.240036811],"iteration":866,"passed_time":0.6105122875,"remaining_time":0.09365413407},
{"learn":[3.238676314],"iteration":867,"passed_time":0.6111600161,"remaining_time":0.09294138494},
{"learn":[3.237848782],"iteration":868,"passed_time":0.6118112163,"remaining_time":0.09222930879},
{"learn":[3.236405498],"iteration":869,"passed_time":0.6125643535,"remaining_time":0.09153260455},
{"learn":[3.233378068],"iteration":870,"passed_time":0.6133538357,"remaining_time":0.09084115363},
{"learn":[3.233169169],"iteration":871,"passed_time":0.6139921976,"remaining_time":0.09012729506},
{"learn":[3.232434885],"iteration":872,"passed_time":0.6150364455,"remaining_time":0.08947265588},
{"learn":[3.229978115],"iteration":873,"passed_time":0.6157795648,"remaining_time":0.088773713},
{"learn":[3.229648848],"iteration":874,"passed_time":0.6162354302,"remaining_time":0.08803363289},
{"learn":[3.227208761],"iteration":875,"passed_time":0.6168225605,"remaining_time":0.08731278253},
{"learn":[3.226258869],"iteration":876,"passed_time":0.6175413562,"remaining_time":0.08661070333},
{"learn":[3.225331995],"iteration":877,"passed_time":0.6181998942,"remaining_time":0.08590021309},
{"learn":[3.221968268],"iteration":878,"passed_time":0.6187953293,"remaining_time":0.08518115455},
{"learn":[3.221166317],"iteration":879,"passed_time":0.6195005408,"remaining_time":0.08447734647},
{"learn":[3.220047503],"iteration":880,"passed_time":0.6200863587,"remaining_time":0.08375740827},
{"learn":[3.21982781],"iteration":881,"passed_time":0.620659574,"remaining_time":0.08303608813},
{"learn":[3.216693405],"iteration":882,"passed_time":0.6231040971,"remaining_time":0.08256305703},
{"learn":[3.214798761],"iteration":883,"passed_time":0.6241538144,"remaining_time":0.08190253673},
{"learn":[3.214395085],"iteration":884,"passed_time":0.6247001116,"remaining_time":0.08117572072},
{"learn":[3.213470696],"iteration":885,"passed_time":0.6251704329,"remaining_time":0.08043953651},
{"learn":[3.211595017],"iteration":886,"passed_time":0.6255545901,"remaining_time":0.07969297483},
{"learn":[3.210965255],"iteration":887,"passed_time":0.6260332363,"remaining_time":0.07895914692},
{"learn":[3.209413583],"iteration":888,"passed_time":0.6266186835,"remaining_time":0.0782392282},
{"learn":[3.208331683],"iteration":889,"passed_time":0.6272245072,"remaining_time":0.0775221301},
{"learn":[3.207110711],"iteration":890,"passed_time":0.6278817128,"remaining_time":0.07681156755},
{"learn":[3.204519413],"iteration":891,"passed_time":0.6283612205,"remaining_time":0.07607960966},
{"learn":[3.201421296],"iteration":892,"passed_time":0.6288871813,"remaining_time":0.0753537832},
{"learn":[3.200691259],"iteration":893,"passed_time":0.6293738719,"remaining_time":0.07462374767},
{"learn":[3.200485067],"iteration":894,"passed_time":0.6302558341,"remaining_time":0.07394062858},
{"learn":[3.197467568],"iteration":895,"passed_time":0.6311948835,"remaining_time":0.07326369183},
{"learn":[3.195838544],"iteration":896,"passed_time":0.6316264154,"remaining_time":0.07252789385},
{"learn":[3.195671746],"iteration":897,"passed_time":0.6320747173,"remaining_time":0.07179467836},
{"learn":[3.194213094],"iteration":898,"passed_time":0.6325879854,"remaining_time":0.07106939547},
{"learn":[3.192884691],"iteration":899,"passed_time":0.633055121,"remaining_time":0.07033945789},
{"learn":[3.188364239],"iteration":900,"passed_time":0.6335097943,"remaining_time":0.06960873434},
{"learn":[3.185219478],"iteration":901,"passed_time":0.6339205791,"remaining_time":0.06887385449},
{"learn":[3.184120387],"iteration":902,"passed_time":0.6344501965,"remaining_time":0.06815245743},
{"learn":[3.183725321],"iteration":903,"passed_time":0.6348952927,"remaining_time":0.06742250896},
{"learn":[3.181264554],"iteration":904,"passed_time":0.6353625785,"remaining_time":0.06669551929},
{"learn":[3.180741589],"iteration":905,"passed_time":0.6359653367,"remaining_time":0.06598315856},
{"learn":[3.179782639],"iteration":906,"passed_time":0.6369631373,"remaining_time":0.0653115455},
{"learn":[3.176377564],"iteration":907,"passed_time":0.6375747714,"remaining_time":0.06460008697},
{"learn":[3.174078182],"iteration":908,"passed_time":0.6383041006,"remaining_time":0.06390063054},
{"learn":[3.171242379],"iteration":909,"passed_time":0.6388641124,"remaining_time":0.06318436276},
{"learn":[3.170421012],"iteration":910,"passed_time":0.6394107201,"remaining_time":0.06246712853},
{"learn":[3.170087224],"iteration":911,"passed_time":0.6403311373,"remaining_time":0.06178633781},
{"learn":[3.167303059],"iteration":912,"passed_time":0.6408488233,"remaining_time":0.06106664581},
{"learn":[3.16705966],"iteration":913,"passed_time":0.6413092068,"remaining_time":0.06034200414},
{"learn":[3.165667683],"iteration":914,"passed_time":0.6418021586,"remaining_time":0.05962096555},
{"learn":[3.164689733],"iteration":915,"passed_time":0.6423262461,"remaining_time":0.05890328021},
{"learn":[3.163311455],"iteration":916,"passed_time":0.6427155525,"remaining_time":0.05817381773},
{"learn":[3.159425016],"iteration":917,"passed_time":0.6432293916,"remaining_time":0.05745622016},
{"learn":[3.159327058],"iteration":918,"passed_time":0.6437108929,"remaining_time":0.0567362158},
{"learn":[3.15819426],"iteration":919,"passed_time":0.6441584334,"remaining_time":0.05601377682},
{"learn":[3.157086603],"iteration":920,"passed_time":0.6447747158,"remaining_time":0.05530640885},
{"learn":[3.153354154],"iteration":921,"passed_time":0.6451810026,"remaining_time":0.0545814731},
{"learn":[3.153261317],"iteration":922,"passed_time":0.6456956732,"remaining_time":0.0538662696},
{"learn":[3.153168454],"iteration":923,"passed_time":0.6461457583,"remaining_time":0.05314618791},
{"learn":[3.152080399],"iteration":924,"passed_time":0.6466259372,"remaining_time":0.05242913005},
{"learn":[3.151635144],"iteration":925,"passed_time":0.6471808999,"remaining_time":0.05171856004},
{"learn":[3.147762655],"iteration":926,"passed_time":0.6477239113,"remaining_time":0.0510073846},
{"learn":[3.147172317],"iteration":927,"passed_time":0.6481766912,"remaining_time":0.05028957087},
{"learn":[3.146254125],"iteration":928,"passed_time":0.6486651149,"remaining_time":0.04957505183},
{"learn":[3.144869828],"iteration":929,"passed_time":0.6491056529,"remaining_time":0.04885741473},
{"learn":[3.143466218],"iteration":930,"passed_time":0.6496027721,"remaining_time":0.04814456635},
{"learn":[3.141919643],"iteration":931,"passed_time":0.650165649,"remaining_time":0.04743697868},
{"learn":[3.141054135],"iteration":932,"passed_time":0.6507643198,"remaining_time":0.04673227163},
{"learn":[3.139390417],"iteration":933,"passed_time":0.6512872052,"remaining_time":0.04602243634},
{"learn":[3.139025283],"iteration":934,"passed_time":0.6518239353,"remaining_time":0.04531396341},
{"learn":[3.137824183],"iteration":935,"passed_time":0.6523752961,"remaining_time":0.04460685785},
{"learn":[3.135620453],"iteration":936,"passed_time":0.6532255671,"remaining_time":0.0439201822},
{"learn":[3.13443178],"iteration":937,"passed_time":0.653910362,"remaining_time":0.04322222009},
{"learn":[3.132765713],"iteration":938,"passed_time":0.6546134797,"remaining_time":0.04252547632},
{"learn":[3.131434124],"iteration":939,"passed_time":0.6552046472,"remaining_time":0.04182157322},
{"learn":[3.128384262],"iteration":940,"passed_time":0.6556132982,"remaining_time":0.04110646609},
{"learn":[3.128120455],"iteration":941,"passed_time":0.6560915637,"remaining_time":0.04039629585},
{"learn":[3.126314615],"iteration":942,"passed_time":0.6565948039,"remaining_time":0.03968812706},
{"learn":[3.125409666],"iteration":943,"passed_time":0.6571806418,"remaining_time":0.03898529231},
{"learn":[3.123072589],"iteration":944,"passed_time":0.6576339426,"remaining_time":0.03827499137},
{"learn":[3.122921099],"iteration":945,"passed_time":0.6582468089,"remaining_time":0.03757434216},
{"learn":[3.122182662],"iteration":946,"passed_time":0.6587024339,"remaining_time":0.03686507814},
{"learn":[3.120040951],"iteration":947,"passed_time":0.6591938329,"remaining_time":0.03615831151},
{"learn":[3.118767799],"iteration":948,"passed_time":0.6598763384,"remaining_time":0.03546226897},
{"learn":[3.118203218],"iteration":949,"passed_time":0.6603844372,"remaining_time":0.03475707564},
{"learn":[3.116343362],"iteration":950,"passed_time":0.6608831994,"remaining_time":0.03405181574},
{"learn":[3.11480829],"iteration":951,"passed_time":0.6613450355,"remaining_time":0.03334512784},
{"learn":[3.112607903],"iteration":952,"passed_time":0.6623627718,"remaining_time":0.03266636965},
{"learn":[3.111661241],"iteration":953,"passed_time":0.6628183367,"remaining_time":0.03195979401},
{"learn":[3.110249676],"iteration":954,"passed_time":0.6633264656,"remaining_time":0.03125622089},
{"learn":[3.107333579],"iteration":955,"passed_time":0.6637357778,"remaining_time":0.0305485086},
{"learn":[3.107149851],"iteration":956,"passed_time":0.6643031226,"remaining_time":0.02984852066},
{"learn":[3.106867336],"iteration":957,"passed_time":0.6648258677,"remaining_time":0.02914685433},
{"learn":[3.10364681],"iteration":958,"passed_time":0.6655014061,"remaining_time":0.02845209348},
{"learn":[3.102703811],"iteration":959,"passed_time":0.6660787288,"remaining_time":0.02775328037},
{"learn":[3.101469264],"iteration":960,"passed_time":0.6666951915,"remaining_time":0.0270563085},
{"learn":[3.09863569],"iteration":961,"passed_time":0.6674843331,"remaining_time":0.02636632501},
{"learn":[3.09645939],"iteration":962,"passed_time":0.6679897672,"remaining_time":0.02566523508},
{"learn":[3.096240186],"iteration":963,"passed_time":0.6684182837,"remaining_time":0.02496167864},
{"learn":[3.094838828],"iteration":964,"passed_time":0.6689092419,"remaining_time":0.02426095696},
{"learn":[3.094176802],"iteration":965,"passed_time":0.6693602186,"remaining_time":0.02355926235},
{"learn":[3.093182279],"iteration":966,"passed_time":0.6697549046,"remaining_time":0.02285616531},
{"learn":[3.090150687],"iteration":967,"passed_time":0.6701653488,"remaining_time":0.02215422641},
{"learn":[3.088612829],"iteration":968,"passed_time":0.6706527406,"remaining_time":0.02145535084},
{"learn":[3.087153684],"iteration":969,"passed_time":0.6710639762,"remaining_time":0.02075455597},
{"learn":[3.085866843],"iteration":970,"passed_time":0.6716238177,"remaining_time":0.02005879579},
{"learn":[3.082669094],"iteration":971,"passed_time":0.6722129315,"remaining_time":0.01936415852},
{"learn":[3.081047548],"iteration":972,"passed_time":0.6726678652,"remaining_time":0.01866601476},
{"learn":[3.079684322],"iteration":973,"passed_time":0.6731046265,"remaining_time":0.01796788531},
{"learn":[3.07613431],"iteration":974,"passed_time":0.673522524,"remaining_time":0.01726980831},
{"learn":[3.074005935],"iteration":975,"passed_time":0.6739078132,"remaining_time":0.0165715036},
{"learn":[3.072988853],"iteration":976,"passed_time":0.674331992,"remaining_time":0.01587475518},
{"learn":[3.072344268],"iteration":977,"passed_time":0.6747526544,"remaining_time":0.01517848507},
{"learn":[3.070654438],"iteration":978,"passed_time":0.6751524596,"remaining_time":0.01448233059},
{"learn":[3.069724506],"iteration":979,"passed_time":0.6756983461,"remaining_time":0.01378976216},
{"learn":[3.067763166],"iteration":980,"passed_time":0.6763963543,"remaining_time":0.01310043907},
{"learn":[3.066737893],"iteration":981,"passed_time":0.6768346879,"remaining_time":0.01240633848},
{"learn":[3.065248174],"iteration":982,"passed_time":0.6772519744,"remaining_time":0.01171239427},
{"learn":[3.063186837],"iteration":983,"passed_time":0.6781924166,"remaining_time":0.01102751897},
{"learn":[3.062880371],"iteration":984,"passed_time":0.6791572717,"remaining_time":0.01034249652},
{"learn":[3.061288645],"iteration":985,"passed_time":0.6796474486,"remaining_time":0.009650166612},
{"learn":[3.059970575],"iteration":986,"passed_time":0.6801364833,"remaining_time":0.00895823129},
{"learn":[3.059576341],"iteration":987,"passed_time":0.680761892,"remaining_time":0.008268363061},
{"learn":[3.058175919],"iteration":988,"passed_time":0.6811876336,"remaining_time":0.007576404418},
{"learn":[3.056830702],"iteration":989,"passed_time":0.6817036065,"remaining_time":0.006885895016},
{"learn":[3.056336579],"iteration":990,"passed_time":0.6820975713,"remaining_time":0.00619462981},
{"learn":[3.055810414],"iteration":991,"passed_time":0.6824966551,"remaining_time":0.005504005283},
{"learn":[3.055476518],"iteration":992,"passed_time":0.6828898184,"remaining_time":0.004813926212},
{"learn":[3.053331734],"iteration":993,"passed_time":0.6834001513,"remaining_time":0.004125151819},
{"learn":[3.050890374],"iteration":994,"passed_time":0.6838122885,"remaining_time":0.003436242656},
{"learn":[3.04972623],"iteration":995,"passed_time":0.6842708588,"remaining_time":0.002748075738},
{"learn":[3.047217327],"iteration":996,"passed_time":0.6848360397,"remaining_time":0.00206069019},
{"learn":[3.047155483],"iteration":997,"passed_time":0.685402258,"remaining_time":0.001373551619},
{"learn":[3.04430671],"iteration":998,"passed_time":0.6859209558,"remaining_time":0.0006866075634},
{"learn":[3.042664195],"iteration":999,"passed_time":0.6864646483,"remaining_time":0}
]}